[
  {
    "seating_no": 1326346,
    "arabic_name": "يهدين عصام عدلى عبدالعظيم",
    "total_degree": 241
  },
  {
    "seating_no": 1597631,
    "arabic_name": "يهدين رضا فكرى محمد بدر عبد الجواد",
    "total_degree": 206.5
  },
  {
    "seating_no": 1599450,
    "arabic_name": "يهدين فوزى رضا محمود الاغا",
    "total_degree": 251
  },
  {
    "seating_no": 1760468,
    "arabic_name": "يهدين ايمن سعيد محمد جابر",
    "total_degree": 136.5
  },
  {
    "seating_no": 1762448,
    "arabic_name": "يهدين محمود احمد محمود عبد العال",
    "total_degree": 260
  },
  {
    "seating_no": 1762449,
    "arabic_name": "يهدين محمود عيد محمود على",
    "total_degree": 278
  }
]