[
  {
    "seating_no": 1574082,
    "arabic_name": "تقى موسى سعد مصطفى سعد",
    "total_degree": 267.5
  },
  {
    "seating_no": 1575469,
    "arabic_name": "تقى محمود مصطفى احمد موافى",
    "total_degree": 212
  },
  {
    "seating_no": 1575723,
    "arabic_name": "تقى خالد على احمد شعيشع",
    "total_degree": 187.5
  },
  {
    "seating_no": 1576094,
    "arabic_name": "تقى محمد احمد مصطفي ندا بصل",
    "total_degree": 287
  },
  {
    "seating_no": 1576314,
    "arabic_name": "تقى عادل محمد السيد حسانين",
    "total_degree": 273
  },
  {
    "seating_no": 1576315,
    "arabic_name": "تقى محمد محمود عبدالله اماره",
    "total_degree": 244
  },
  {
    "seating_no": 1576826,
    "arabic_name": "تقى خالد محمود محمد الزغل",
    "total_degree": 212
  },
  {
    "seating_no": 1577087,
    "arabic_name": "تقى محمد زكى محمد حفيشة",
    "total_degree": 231
  },
  {
    "seating_no": 1577480,
    "arabic_name": "تقى حاتم فتوح غله",
    "total_degree": 290.5
  },
  {
    "seating_no": 1577746,
    "arabic_name": "تقى ممدوح مسعد محمد خميس",
    "total_degree": 200
  },
  {
    "seating_no": 1581503,
    "arabic_name": "تقوى محمد سادات محمد شتيه",
    "total_degree": 240
  },
  {
    "seating_no": 1581504,
    "arabic_name": "تقى احمد السيد احمد منصور",
    "total_degree": 254
  },
  {
    "seating_no": 1581505,
    "arabic_name": "تقى رضا عبد الفتاح ابراهيم العنانى",
    "total_degree": 232
  },
  {
    "seating_no": 1581506,
    "arabic_name": "تقى عصام الدين احمد البيومى سالم",
    "total_degree": 195
  },
  {
    "seating_no": 1582163,
    "arabic_name": "تقى فؤاد صادق حسن السقعان",
    "total_degree": 276.5
  },
  {
    "seating_no": 1582346,
    "arabic_name": "تقى أيمن ابراهيم البرعى ابراهيم",
    "total_degree": 194
  },
  {
    "seating_no": 1582467,
    "arabic_name": "تقى احمد عبدالمنعم محمد الرفاعى",
    "total_degree": 245.5
  },
  {
    "seating_no": 1582923,
    "arabic_name": "تقى خالد عبدالوهاب عبدالمنعم عز",
    "total_degree": 224
  },
  {
    "seating_no": 1582924,
    "arabic_name": "تقى عمرو محمد عبدالمنعم رخا",
    "total_degree": 294.5
  },
  {
    "seating_no": 1583660,
    "arabic_name": "تقى انور سعد احمد بدير",
    "total_degree": 295.5
  },
  {
    "seating_no": 1584504,
    "arabic_name": "تقى السيد فايد غنيم",
    "total_degree": 207.5
  },
  {
    "seating_no": 1584505,
    "arabic_name": "تقى عبده حامد الدرسى",
    "total_degree": 257.5
  },
  {
    "seating_no": 1584606,
    "arabic_name": "تقى أحمد ابراهيم أبوسالم",
    "total_degree": 278.5
  },
  {
    "seating_no": 1585544,
    "arabic_name": "تقى أيمن زينهم أبو شبانه شتا",
    "total_degree": 203
  },
  {
    "seating_no": 1586297,
    "arabic_name": "تقى الشافعى محمد امين زهران",
    "total_degree": 258
  },
  {
    "seating_no": 1586298,
    "arabic_name": "تقى عاشور عاشور السيد",
    "total_degree": 268
  },
  {
    "seating_no": 1586617,
    "arabic_name": "تقى خالد فوزى عبيه",
    "total_degree": 274
  },
  {
    "seating_no": 1587035,
    "arabic_name": "تقى موسى عبد الحافظ موسى غنيم",
    "total_degree": 201
  },
  {
    "seating_no": 1587123,
    "arabic_name": "تقى محمود سالم سيداحمد",
    "total_degree": 235.5
  },
  {
    "seating_no": 1587203,
    "arabic_name": "تقى احمد محمد الامام",
    "total_degree": 216
  },
  {
    "seating_no": 1589105,
    "arabic_name": "تقى عماد يسن محمد السيد زعيمه",
    "total_degree": 240
  },
  {
    "seating_no": 1589751,
    "arabic_name": "تقى حسام  الدين مصطفى الرميسى",
    "total_degree": 242.5
  },
  {
    "seating_no": 1589776,
    "arabic_name": "تقى حاتم السيد محمد المهدى",
    "total_degree": 171.5
  },
  {
    "seating_no": 1590087,
    "arabic_name": "تقى فتحى قاسم احمد قاسم",
    "total_degree": 255.5
  },
  {
    "seating_no": 1590088,
    "arabic_name": "تقى محمد عبداللطيف عبدالحافظ لقمه",
    "total_degree": 208.5
  },
  {
    "seating_no": 1590853,
    "arabic_name": "تقى عبدالشهيد صالح عبدالعظيم صالح جرد",
    "total_degree": 209.5
  },
  {
    "seating_no": 1591157,
    "arabic_name": " تقى محمود عبد الحميد عبد الفضيل الجمل",
    "total_degree": 204.5
  },
  {
    "seating_no": 1591372,
    "arabic_name": "تقى خالد على السيد عجيل",
    "total_degree": 293
  },
  {
    "seating_no": 1591558,
    "arabic_name": "تقى يحى رشاد رضوان",
    "total_degree": 190.5
  },
  {
    "seating_no": 1591698,
    "arabic_name": "تقى سامى محمد مرسى الشيخ",
    "total_degree": 210.5
  },
  {
    "seating_no": 1591711,
    "arabic_name": "تقى ابراهيم محمد اسماعيل محمد",
    "total_degree": 242.5
  },
  {
    "seating_no": 1591857,
    "arabic_name": "تقى حسام الدين سرور عيسى عثمان",
    "total_degree": 199
  },
  {
    "seating_no": 1591858,
    "arabic_name": "تقى عيد ابراهيم عيد البدوى",
    "total_degree": 112
  },
  {
    "seating_no": 1592201,
    "arabic_name": "تقى مصطفى راغب الشال",
    "total_degree": 177
  },
  {
    "seating_no": 1592321,
    "arabic_name": "تقى مصطفى عبدالمعطى عمر سلام",
    "total_degree": 230
  },
  {
    "seating_no": 1592816,
    "arabic_name": "تقى محمد محمد حامد الفيومى",
    "total_degree": 181.5
  },
  {
    "seating_no": 1592817,
    "arabic_name": "تقى محمد محمد هاشم الغرباوى",
    "total_degree": 232.5
  },
  {
    "seating_no": 1593116,
    "arabic_name": "تقى عبدالعزيز ابراهيم عبدالعزيز الشافعى",
    "total_degree": 193.5
  },
  {
    "seating_no": 1594485,
    "arabic_name": "تقى اشرف احمد البغدادي",
    "total_degree": 256.5
  },
  {
    "seating_no": 1595641,
    "arabic_name": "تقى احمد عبد الرحمن خطاب عبد السميع",
    "total_degree": 228.5
  },
  {
    "seating_no": 1595842,
    "arabic_name": "تقى ايمن فؤاد محمد محمد",
    "total_degree": 215
  },
  {
    "seating_no": 1595843,
    "arabic_name": "تقى سامى محمد محمد الشهاوى",
    "total_degree": 178
  },
  {
    "seating_no": 1597786,
    "arabic_name": "تقى تامر محمد محمد سرحان",
    "total_degree": 209
  },
  {
    "seating_no": 1598016,
    "arabic_name": "تقى احمد رمضان العيوطى",
    "total_degree": 193
  },
  {
    "seating_no": 1605905,
    "arabic_name": "تقى ممدوح الدسوقى ابو زهرة",
    "total_degree": 252
  },
  {
    "seating_no": 1606119,
    "arabic_name": "تقى حسن محمد عادل محمد حسن",
    "total_degree": 217
  },
  {
    "seating_no": 1608125,
    "arabic_name": "تقى عزات احمد بوارشي",
    "total_degree": 165
  },
  {
    "seating_no": 1610320,
    "arabic_name": "تقى احمد ابريشه صالح ابريشه",
    "total_degree": 265
  },
  {
    "seating_no": 1610340,
    "arabic_name": "تقى اشرف صبحى محمد الخياط",
    "total_degree": 222
  },
  {
    "seating_no": 1610565,
    "arabic_name": "تقى عبدالرحمن ماهر عبدالرحمن السيد",
    "total_degree": 275
  },
  {
    "seating_no": 1611243,
    "arabic_name": "تقى احمد فاروق الشحات",
    "total_degree": 156
  },
  {
    "seating_no": 1611997,
    "arabic_name": "تقوى سند النادى سند حسين",
    "total_degree": 214.5
  },
  {
    "seating_no": 1611998,
    "arabic_name": "تقى طارق عبدالعزيز محمد عبدالعزيز",
    "total_degree": 258
  },
  {
    "seating_no": 1611999,
    "arabic_name": "تقى مصطفى حسين محمد على",
    "total_degree": 220
  },
  {
    "seating_no": 1612237,
    "arabic_name": "تقوى ضياء محمد عوض اسماعيل",
    "total_degree": 227
  },
  {
    "seating_no": 1612432,
    "arabic_name": "تقوى نبيل محمد شعبان عطيه عوض",
    "total_degree": 192
  },
  {
    "seating_no": 1612937,
    "arabic_name": "تقى محمد صلاح محمد على راشد",
    "total_degree": 171.5
  },
  {
    "seating_no": 1613400,
    "arabic_name": "تقى عصام شوقى ابراهيم بدوى",
    "total_degree": 174.5
  },
  {
    "seating_no": 1614348,
    "arabic_name": "تقين رمضان عبدالفتاح سليم عبدالرحمن",
    "total_degree": 244.5
  },
  {
    "seating_no": 1614471,
    "arabic_name": "تقى محمد نوفل على محمود",
    "total_degree": 292
  },
  {
    "seating_no": 1614472,
    "arabic_name": "تقى ناصر فهمى محمد الزناتى",
    "total_degree": 237.5
  },
  {
    "seating_no": 1614473,
    "arabic_name": "تقى ناصر محمد عطيه محمد",
    "total_degree": 281
  },
  {
    "seating_no": 1614474,
    "arabic_name": "تقى هانى عبدالسلام محمد السيد الشحات",
    "total_degree": 191
  },
  {
    "seating_no": 1614475,
    "arabic_name": "تقى هانى عبدالغفار امين السيد",
    "total_degree": 172
  },
  {
    "seating_no": 1614476,
    "arabic_name": "تقى هشام أحمد عبدالبديع محمد بيومى الهضيبى",
    "total_degree": 168.5
  },
  {
    "seating_no": 1615787,
    "arabic_name": "تقوى وائل محمد المنير مصطفى",
    "total_degree": 225.5
  },
  {
    "seating_no": 1615788,
    "arabic_name": "تقى وليد محمد السيد شحاته",
    "total_degree": 234
  },
  {
    "seating_no": 1616536,
    "arabic_name": "تقى السيد عبده السيد حجاج",
    "total_degree": 247
  },
  {
    "seating_no": 1616537,
    "arabic_name": "تقى مصطفى عبد العزيز على ابراهيم",
    "total_degree": 207
  },
  {
    "seating_no": 1616984,
    "arabic_name": "تقى توفيق جلال توفيق مصطفى",
    "total_degree": 229.5
  },
  {
    "seating_no": 1616985,
    "arabic_name": "تقى نجم محمد نجم حسانين",
    "total_degree": 228.5
  },
  {
    "seating_no": 1617153,
    "arabic_name": "تقى محمود انور محمود ابراهيم",
    "total_degree": 226.5
  },
  {
    "seating_no": 1617154,
    "arabic_name": "تقى مكاوى عبدالفتاح امام مكاوى",
    "total_degree": 255
  },
  {
    "seating_no": 1619247,
    "arabic_name": "تقى احمد محمد ابراهيم اسماعيل",
    "total_degree": 181.5
  },
  {
    "seating_no": 1620666,
    "arabic_name": "تقى فاروق محمود غريب شريف",
    "total_degree": 219
  },
  {
    "seating_no": 1621266,
    "arabic_name": "تقى محمد رسلان عبدالعزيز عبدالحميد",
    "total_degree": 260
  },
  {
    "seating_no": 1622096,
    "arabic_name": "تقى احمد الشرقاوى على حسين",
    "total_degree": 262
  },
  {
    "seating_no": 1622212,
    "arabic_name": "تقى احمد السيد بركات محمد",
    "total_degree": 179.5
  },
  {
    "seating_no": 1623678,
    "arabic_name": "تقى محمود عبدالرحمن المهدى محمد",
    "total_degree": 208.5
  },
  {
    "seating_no": 1623976,
    "arabic_name": "تقى محمد سامى محمد ابراهيم",
    "total_degree": 234
  },
  {
    "seating_no": 1624079,
    "arabic_name": "تقى عبد العزيز فتحى كامل عبد المعطى",
    "total_degree": 274
  },
  {
    "seating_no": 1627003,
    "arabic_name": "تقى سوهيل احمد محمد احمد",
    "total_degree": 266
  },
  {
    "seating_no": 1627004,
    "arabic_name": "تقى معتز عبدالسلام ثابت عطا الله الصادى",
    "total_degree": 275
  },
  {
    "seating_no": 1627566,
    "arabic_name": "تقى عصام السيد العربي أمين محمد",
    "total_degree": 278.5
  },
  {
    "seating_no": 1628455,
    "arabic_name": "تقى رمضان احمد رمضان سالم",
    "total_degree": 238.5
  },
  {
    "seating_no": 1629419,
    "arabic_name": "تقى عبده ابراهيم متولي ابراهيم",
    "total_degree": 239.5
  },
  {
    "seating_no": 1629905,
    "arabic_name": "تقوى صلاح على على مسعود",
    "total_degree": 207
  },
  {
    "seating_no": 1631166,
    "arabic_name": "تقوى رمضان محمد توفيق سلامه",
    "total_degree": 276
  },
  {
    "seating_no": 1640155,
    "arabic_name": "تقى محمد مصطفى حامد الشرقاوى",
    "total_degree": 0
  },
  {
    "seating_no": 1640655,
    "arabic_name": "تقى مصطفى محمود عبد الجواد الشاعر",
    "total_degree": 255
  },
  {
    "seating_no": 1640680,
    "arabic_name": "تقى وائل ابو ماضى عبد اللطيف",
    "total_degree": 271.5
  },
  {
    "seating_no": 1641789,
    "arabic_name": "تقى احمد خليفه خليفه محمود عبد الله",
    "total_degree": 268.5
  },
  {
    "seating_no": 1642190,
    "arabic_name": "تقى علاء محمد عبد العاطى يوسف",
    "total_degree": 298.5
  },
  {
    "seating_no": 1642600,
    "arabic_name": "تقى الدين ابراهيم ابو بكر محمد عبد الجواد",
    "total_degree": 249
  },
  {
    "seating_no": 1644552,
    "arabic_name": "تقوى احمد مصطفى نصر مصطفى الموجى",
    "total_degree": 195.5
  },
  {
    "seating_no": 1644942,
    "arabic_name": "تقى على محمد احمد محمد",
    "total_degree": 244
  },
  {
    "seating_no": 1645795,
    "arabic_name": "تقوى يحيى فتحى محمد سليم",
    "total_degree": 257
  },
  {
    "seating_no": 1652596,
    "arabic_name": "تقى ابراهيم محمود ابراهيم محمد عثمان",
    "total_degree": 216
  },
  {
    "seating_no": 1654550,
    "arabic_name": "تقى عبد العزيز محمد عبد العزيز الشربينى المناو",
    "total_degree": 190
  },
  {
    "seating_no": 1654551,
    "arabic_name": "تقى عمرو محمد السيد غراب",
    "total_degree": 259.5
  },
  {
    "seating_no": 1654982,
    "arabic_name": "تقوى اكرامى مختار مخيمر",
    "total_degree": 171.5
  },
  {
    "seating_no": 1654983,
    "arabic_name": "تقوى محمد احمد الامام",
    "total_degree": 235
  },
  {
    "seating_no": 1655549,
    "arabic_name": "تقا محمد رشاد احمد محمد",
    "total_degree": 162
  },
  {
    "seating_no": 1655953,
    "arabic_name": "تقى حسن نصر الشحات نصر",
    "total_degree": 281
  },
  {
    "seating_no": 1657262,
    "arabic_name": "تقى احمد حمدى حسن محمد الجمال",
    "total_degree": 275
  },
  {
    "seating_no": 1657606,
    "arabic_name": "تقى محمد سعد عبد الله احمد",
    "total_degree": 136
  },
  {
    "seating_no": 1657674,
    "arabic_name": "تقوى رمزى عبد الرازق عبد اللطيف هاشم",
    "total_degree": 172
  },
  {
    "seating_no": 1657755,
    "arabic_name": "تقى ايمن شربجى .",
    "total_degree": 221
  },
  {
    "seating_no": 1659100,
    "arabic_name": "تقى احمد عبد الحميد عباس الجندى",
    "total_degree": 189
  },
  {
    "seating_no": 1661330,
    "arabic_name": "تقى وائل سعد ابراهيم الحرش",
    "total_degree": 238.5
  },
  {
    "seating_no": 1669971,
    "arabic_name": "تقى اسامه على حامد عثمان",
    "total_degree": 254
  },
  {
    "seating_no": 1672145,
    "arabic_name": "تقى وليد فوزى محمود عوض",
    "total_degree": 181.5
  },
  {
    "seating_no": 1673589,
    "arabic_name": "تقى اشرف شوقى زاهر محمد",
    "total_degree": 207.5
  },
  {
    "seating_no": 1674001,
    "arabic_name": "تقوى محمد موسى عثمان موسى",
    "total_degree": 222.5
  },
  {
    "seating_no": 1674695,
    "arabic_name": "تقى مصطفى محمد الشحات السيد عجوه",
    "total_degree": 248
  },
  {
    "seating_no": 1677568,
    "arabic_name": "تقى ايمن سلامه مهدى سلامه",
    "total_degree": 244.5
  },
  {
    "seating_no": 1678564,
    "arabic_name": "تقى محمود محسن محمد حسن",
    "total_degree": 231
  },
  {
    "seating_no": 1679953,
    "arabic_name": "تقوى اشرف امين حسن السيد",
    "total_degree": 256.5
  },
  {
    "seating_no": 1679954,
    "arabic_name": "تقوى مصطفى عبد الوهاب عبد السميع",
    "total_degree": 260.5
  },
  {
    "seating_no": 1682521,
    "arabic_name": "تقى عصام الشحات عبد العزيز عبد العزيز",
    "total_degree": 214.5
  },
  {
    "seating_no": 1683152,
    "arabic_name": "تقى ايمن احمد سيد احمد محمد المدابغى",
    "total_degree": 215.5
  },
  {
    "seating_no": 1683871,
    "arabic_name": "تقوى محمود محمد عبد الفتاح احمد",
    "total_degree": 254
  },
  {
    "seating_no": 1684895,
    "arabic_name": "تقى احمد السعيد سعد جادو",
    "total_degree": 266
  },
  {
    "seating_no": 1684896,
    "arabic_name": "تقى مجدى المرزوقى محمود محمد الشامى",
    "total_degree": 298.5
  },
  {
    "seating_no": 1685101,
    "arabic_name": "تقى محمد يحيى عبد الحميد الستاوى",
    "total_degree": 193
  },
  {
    "seating_no": 1685386,
    "arabic_name": "تقى ايهاب صلاح عبد الحميد متولى الالفى",
    "total_degree": 221
  },
  {
    "seating_no": 1686056,
    "arabic_name": "تقى على محمد متولى السيد بدر",
    "total_degree": 254
  },
  {
    "seating_no": 1686089,
    "arabic_name": "تقى احمد سلامه عطيه محمد عقل",
    "total_degree": 200.5
  },
  {
    "seating_no": 1686664,
    "arabic_name": "تقى ايمن صلاح عيسى عبد الله",
    "total_degree": 234.5
  },
  {
    "seating_no": 1687473,
    "arabic_name": "تقى وائل محمد حامد الجوهرى",
    "total_degree": 249.5
  },
  {
    "seating_no": 1690775,
    "arabic_name": "تقى حامد مخيمر حامد مخيمر",
    "total_degree": 282
  },
  {
    "seating_no": 1691074,
    "arabic_name": "تقى خالد عبد السلام محمود عبد السلام",
    "total_degree": 285
  },
  {
    "seating_no": 1700263,
    "arabic_name": "تقى احمد الرفاعى محمد الدسوقى",
    "total_degree": 286
  },
  {
    "seating_no": 1700264,
    "arabic_name": "تقى الحسين السيد محمد محمد",
    "total_degree": 258
  },
  {
    "seating_no": 1700265,
    "arabic_name": "تقى العربى السيد احمد شعبان",
    "total_degree": 299.5
  },
  {
    "seating_no": 1700266,
    "arabic_name": "تقى حسن محمد عبد الغفار حسن",
    "total_degree": 294.5
  },
  {
    "seating_no": 1700267,
    "arabic_name": "تقى محمد لبيب لبيب محمد فهيد",
    "total_degree": 301.5
  },
  {
    "seating_no": 1700268,
    "arabic_name": "تقى محمد محمد السعيد سليم",
    "total_degree": 301.5
  },
  {
    "seating_no": 1700269,
    "arabic_name": "تقى محمد محمد حسن صالح",
    "total_degree": 299.5
  },
  {
    "seating_no": 1701510,
    "arabic_name": "تقى محمد سيد احمد طه الامير",
    "total_degree": 222
  },
  {
    "seating_no": 1701511,
    "arabic_name": "تقى هندى محمد محمد موسى",
    "total_degree": 296
  },
  {
    "seating_no": 1702743,
    "arabic_name": "تقى محمد محمد محمد العاصى",
    "total_degree": 282
  },
  {
    "seating_no": 1710541,
    "arabic_name": "تقى سمير عبد المنعم على توفيق ابو العلا",
    "total_degree": 206
  },
  {
    "seating_no": 1710616,
    "arabic_name": "تقى حسن عبد الفتاح حسن بندق",
    "total_degree": 188.5
  },
  {
    "seating_no": 1711051,
    "arabic_name": "تقى ياسر عبد الرحمن احمد يعقوب",
    "total_degree": 252.5
  },
  {
    "seating_no": 1712537,
    "arabic_name": "تقى شرقاوى فراج سليمان احمد",
    "total_degree": 208.5
  },
  {
    "seating_no": 1712771,
    "arabic_name": "تقى طارق لطفى عبدالحميد شرف الدين",
    "total_degree": 250.5
  },
  {
    "seating_no": 1712950,
    "arabic_name": "تقى عادل ابراهيم محمد جعفر",
    "total_degree": 262.5
  },
  {
    "seating_no": 1714083,
    "arabic_name": "تقى تامر حامد السيد الزينى",
    "total_degree": 273.5
  },
  {
    "seating_no": 1715287,
    "arabic_name": "تقى محمد مسعد السيد هلال",
    "total_degree": 248.5
  },
  {
    "seating_no": 1715670,
    "arabic_name": "تقى محمد محمود حسن محمد جاد المولى",
    "total_degree": 277.5
  },
  {
    "seating_no": 1715734,
    "arabic_name": "تقى محمد جمعه محمد جمعه",
    "total_degree": 258
  },
  {
    "seating_no": 1715897,
    "arabic_name": "تقى محمد الغريب عبد العال صبح الفار",
    "total_degree": 163
  },
  {
    "seating_no": 1716865,
    "arabic_name": "تقي الدين علي احمد عمر زين الدين",
    "total_degree": 291.5
  },
  {
    "seating_no": 1717720,
    "arabic_name": "تقى أحمد ابراهيم يوسف السيد",
    "total_degree": 188
  },
  {
    "seating_no": 1717829,
    "arabic_name": "تقوى عبده عبد النبى ابراهيم السيد",
    "total_degree": 190
  },
  {
    "seating_no": 1718094,
    "arabic_name": "تقى على مصطفى محمد مصطفى شطا",
    "total_degree": 262
  },
  {
    "seating_no": 1718275,
    "arabic_name": "تقى محمد عثمان سراج الدين خطاب",
    "total_degree": 208
  },
  {
    "seating_no": 1718999,
    "arabic_name": "تقىء أحمد حسن السيد سلامه",
    "total_degree": 197.5
  },
  {
    "seating_no": 1719841,
    "arabic_name": "تقى خالد غريب السيد احمد",
    "total_degree": 240.5
  },
  {
    "seating_no": 1720180,
    "arabic_name": "تقوى ياسر الهادى احمد على",
    "total_degree": 193.5
  },
  {
    "seating_no": 1721740,
    "arabic_name": "تقى امير كامل محمد",
    "total_degree": 299.5
  },
  {
    "seating_no": 1722678,
    "arabic_name": "تقوى ايمن عوض صايم حسين",
    "total_degree": 182
  },
  {
    "seating_no": 1722679,
    "arabic_name": "تقى السيد فوزى عبد الرازق",
    "total_degree": 117
  },
  {
    "seating_no": 1724764,
    "arabic_name": "تقى محمد مدحت محمود محمد مراد",
    "total_degree": 297.5
  },
  {
    "seating_no": 1724954,
    "arabic_name": "تقى عباس محمود محمد على",
    "total_degree": 187
  },
  {
    "seating_no": 1725366,
    "arabic_name": "تقى احمد عبد الرحيم عبد المطلب موسى",
    "total_degree": 245.5
  },
  {
    "seating_no": 1725610,
    "arabic_name": "تقى احمد حسين على على النجار",
    "total_degree": 216.5
  },
  {
    "seating_no": 1725611,
    "arabic_name": "تقى عماد فؤاد احمد سلامة",
    "total_degree": 218
  },
  {
    "seating_no": 1726228,
    "arabic_name": "تقى معتز السيد محمد ابوزيد",
    "total_degree": 208.5
  },
  {
    "seating_no": 1726472,
    "arabic_name": "تقى طارق حسانين امام حسانين",
    "total_degree": 221
  },
  {
    "seating_no": 1726682,
    "arabic_name": "تقى سعيد محمد على عابد",
    "total_degree": 174
  },
  {
    "seating_no": 1727081,
    "arabic_name": "تقى سعيد السيد مصطفى عبدالرحمن",
    "total_degree": 214
  },
  {
    "seating_no": 1727932,
    "arabic_name": "تقى ايمن محمد حسن فرحات",
    "total_degree": 220
  },
  {
    "seating_no": 1728348,
    "arabic_name": "تقى احمد السيد عبدالمجيد محمد",
    "total_degree": 251.5
  },
  {
    "seating_no": 1728818,
    "arabic_name": "تقى سامح احمد محمد عزت الحمراوى",
    "total_degree": 306.5
  },
  {
    "seating_no": 1729485,
    "arabic_name": "تقى جمال السيد سليم داود",
    "total_degree": 190.5
  },
  {
    "seating_no": 1731465,
    "arabic_name": "تقوى محمد السيد محمد",
    "total_degree": 229
  },
  {
    "seating_no": 1731466,
    "arabic_name": "تقوى مصطفى محمد فتحى بغدادى مصطفى",
    "total_degree": 241.5
  },
  {
    "seating_no": 1733155,
    "arabic_name": "تقى ايمن عبد المنعم محمد",
    "total_degree": 295
  },
  {
    "seating_no": 1733156,
    "arabic_name": "تقى ايهاب احمد فتحي محمد سالم",
    "total_degree": 240
  },
  {
    "seating_no": 1733157,
    "arabic_name": "تقى عيسى فاروق محمد الصادق",
    "total_degree": 234.5
  },
  {
    "seating_no": 1734061,
    "arabic_name": "تقى عطيه على ابوتريه عطيه",
    "total_degree": 261.5
  },
  {
    "seating_no": 1734486,
    "arabic_name": "تقوى محمد حسنين حسين",
    "total_degree": 206.5
  },
  {
    "seating_no": 1734554,
    "arabic_name": "تقى وائل السيد ابراهيم محمد",
    "total_degree": 191
  },
  {
    "seating_no": 1735444,
    "arabic_name": "تقى طارق محمد السيد حسين",
    "total_degree": 297
  },
  {
    "seating_no": 1736475,
    "arabic_name": "تقى حازم محمد محمد العدوى",
    "total_degree": 260.5
  },
  {
    "seating_no": 1736476,
    "arabic_name": "تقى عاطف محمد امين عبدالفتاح",
    "total_degree": 302
  },
  {
    "seating_no": 1736826,
    "arabic_name": "تقى أكرم طه حسين عبدالجليل",
    "total_degree": 232.5
  },
  {
    "seating_no": 1736827,
    "arabic_name": "تقى السيد عبدالرازق السيد عبدالرازق",
    "total_degree": 194
  },
  {
    "seating_no": 1736828,
    "arabic_name": "تقى محمد محمد السعيد احمد سيد احمد",
    "total_degree": 171
  },
  {
    "seating_no": 1737320,
    "arabic_name": "تقى احمد محمد فتحى السيد شاهين",
    "total_degree": 235.5
  },
  {
    "seating_no": 1738683,
    "arabic_name": "تقى تامر محمد نصر",
    "total_degree": 251.5
  },
  {
    "seating_no": 1739057,
    "arabic_name": "تقى السيد سعيد محمد السيد",
    "total_degree": 285
  },
  {
    "seating_no": 1740215,
    "arabic_name": "تقى احمد محمد نجيب محمد ابراهيم",
    "total_degree": 196
  },
  {
    "seating_no": 1741789,
    "arabic_name": "تقى محمد صلاح الدين ابراهيم محمد",
    "total_degree": 155.5
  },
  {
    "seating_no": 1741934,
    "arabic_name": "تقى السيد سعيد احمد الربع",
    "total_degree": 184
  },
  {
    "seating_no": 1742287,
    "arabic_name": "تقى عماد عبدالحميد عطوة حبيش",
    "total_degree": 268.5
  },
  {
    "seating_no": 1742288,
    "arabic_name": "تقى محمد ابراهيم محمد البكش",
    "total_degree": 239.5
  },
  {
    "seating_no": 1742438,
    "arabic_name": "تقى وليد محمد محمد خضر",
    "total_degree": 214.5
  },
  {
    "seating_no": 1742512,
    "arabic_name": "تقي عبد الناصر محمد عبده حسن",
    "total_degree": 212.5
  },
  {
    "seating_no": 1742797,
    "arabic_name": "تقوى السيد قاسم صالح على الجيزاوى",
    "total_degree": 246.5
  },
  {
    "seating_no": 1742937,
    "arabic_name": "تقى محمد ابراهيم عبدالحليم محمد",
    "total_degree": 212.5
  },
  {
    "seating_no": 1743081,
    "arabic_name": "تقى هشام محمود محمدالسيد",
    "total_degree": 273.5
  },
  {
    "seating_no": 1743685,
    "arabic_name": "تقى محمد عبدالرحمن عبدالفتاح محمد",
    "total_degree": 223
  },
  {
    "seating_no": 1744145,
    "arabic_name": "تقى رضا احمد عبد الغنى عبد الرحمن",
    "total_degree": 181
  },
  {
    "seating_no": 1744881,
    "arabic_name": "تقى ايهاب احمد محمد طنطاوى",
    "total_degree": 206.5
  },
  {
    "seating_no": 1744882,
    "arabic_name": "تقى كحلاوى محمد محمود غنية",
    "total_degree": 180
  },
  {
    "seating_no": 1745393,
    "arabic_name": "تقى امير كمال محمد علي العياط",
    "total_degree": 224
  },
  {
    "seating_no": 1745394,
    "arabic_name": "تقى حمدى نصر السيد نصر",
    "total_degree": 181.5
  },
  {
    "seating_no": 1745805,
    "arabic_name": "تقى جمال محمد عبد العزيز عثمان",
    "total_degree": 133.5
  },
  {
    "seating_no": 1745923,
    "arabic_name": "تقى حسين عبدالغنى حسين مصطفى",
    "total_degree": 121
  },
  {
    "seating_no": 1746799,
    "arabic_name": "تقوى عصام عبد السلام عبد الله",
    "total_degree": 253
  },
  {
    "seating_no": 1746800,
    "arabic_name": "تقى مصطفى السيد مصطفى السيد",
    "total_degree": 212.5
  },
  {
    "seating_no": 1747280,
    "arabic_name": "تقى هانى عطيه السيد عطيه يوسف",
    "total_degree": 264
  },
  {
    "seating_no": 1747347,
    "arabic_name": "تقى هشام عبدالسلام السيد",
    "total_degree": 196.5
  },
  {
    "seating_no": 1748019,
    "arabic_name": "تقى علاء فتحى توفيق محمد",
    "total_degree": 187.5
  },
  {
    "seating_no": 1748563,
    "arabic_name": "تقوى محمد فؤاد ابراهيم حسن",
    "total_degree": 199.5
  },
  {
    "seating_no": 1750962,
    "arabic_name": "تقى على محمد حسن محمد",
    "total_degree": 278.5
  },
  {
    "seating_no": 1751197,
    "arabic_name": "تقى عبدالستار احمد حسن على",
    "total_degree": 290
  },
  {
    "seating_no": 1751198,
    "arabic_name": "تقى عمادالدين على ابراهيم سلامه",
    "total_degree": 276.5
  },
  {
    "seating_no": 1751199,
    "arabic_name": "تقى محمد احمد السيد سليمان",
    "total_degree": 297.5
  },
  {
    "seating_no": 1752850,
    "arabic_name": "تقى ايهاب السيد سليمان  هنداوى",
    "total_degree": 250
  },
  {
    "seating_no": 1753203,
    "arabic_name": "تقى حشمت عبد الحميد محمد موسي",
    "total_degree": 284
  },
  {
    "seating_no": 1753800,
    "arabic_name": "تقى احمد ابراهيم سكران عبيد",
    "total_degree": 137.5
  },
  {
    "seating_no": 1753990,
    "arabic_name": "تقى عماد سمير مصطفى بيومى ابو معزه",
    "total_degree": 185.5
  },
  {
    "seating_no": 1754477,
    "arabic_name": "تقى ياسر احمد عبدالحميد بصيرى",
    "total_degree": 189
  },
  {
    "seating_no": 1754703,
    "arabic_name": "تقى احمد محمد عبداللطيف سلامه",
    "total_degree": 229
  },
  {
    "seating_no": 1754704,
    "arabic_name": "تقى بهاء بيومى عليوة عواد",
    "total_degree": 193.5
  },
  {
    "seating_no": 1754727,
    "arabic_name": "تقى ياسر رضا محمد تهامى",
    "total_degree": 140
  },
  {
    "seating_no": 1754881,
    "arabic_name": "تقي احمد محمد عبدالله محمد الحلبي",
    "total_degree": 169
  },
  {
    "seating_no": 1754950,
    "arabic_name": "تقى السيد مصطفى حسين عليوه",
    "total_degree": 186.5
  },
  {
    "seating_no": 1755358,
    "arabic_name": "تقى حمدى السيد احمد مصطفى",
    "total_degree": 222
  },
  {
    "seating_no": 1755359,
    "arabic_name": "تقى عماد عبدالمنعم اسماعيل رمضان",
    "total_degree": 199
  },
  {
    "seating_no": 1756484,
    "arabic_name": "تقوى جمعه عبد العزيز فرج",
    "total_degree": 188.5
  },
  {
    "seating_no": 1756564,
    "arabic_name": "تقوي السيد عبدالحليم السيد",
    "total_degree": 250.5
  },
  {
    "seating_no": 1756600,
    "arabic_name": "تقوى ياسر محمد سالم محمد",
    "total_degree": 211.5
  },
  {
    "seating_no": 1756601,
    "arabic_name": "تقى ياسر محمد سالم محمد",
    "total_degree": 219.5
  },
  {
    "seating_no": 1756716,
    "arabic_name": "تقى علاء السيد بيومى ابراهيم",
    "total_degree": 205
  },
  {
    "seating_no": 1757544,
    "arabic_name": "تقى محمد ابراهيم احمد حميده",
    "total_degree": 186
  },
  {
    "seating_no": 1757692,
    "arabic_name": "تقى محمد عبدالقادر احمد إبراهيم",
    "total_degree": 222.5
  },
  {
    "seating_no": 1758649,
    "arabic_name": "تقى عادل عزمى محمد عبدالعزيز",
    "total_degree": 214.5
  },
  {
    "seating_no": 1759716,
    "arabic_name": "تقى عبدالعال محمد على عبد العال نويره",
    "total_degree": 300.5
  },
  {
    "seating_no": 1759926,
    "arabic_name": "تقى على برمو ",
    "total_degree": 286
  },
  {
    "seating_no": 1762066,
    "arabic_name": "تقى احمد سلمى محمد عوض",
    "total_degree": 284.5
  },
  {
    "seating_no": 1762067,
    "arabic_name": "تقى تامر محمد نصار العبد",
    "total_degree": 262
  },
  {
    "seating_no": 1762543,
    "arabic_name": "تقى جهاد عبد ربه محمود",
    "total_degree": 230
  },
  {
    "seating_no": 1763056,
    "arabic_name": "تقى حازم احمد النحال",
    "total_degree": 272.5
  },
  {
    "seating_no": 1763629,
    "arabic_name": "تقي فتحى حمدان نصير",
    "total_degree": 260
  },
  {
    "seating_no": 1764498,
    "arabic_name": "تقى محمود ناصر سليمان",
    "total_degree": 220
  },
  {
    "seating_no": 1776185,
    "arabic_name": "تقى حسين محمد محمود",
    "total_degree": 207.5
  },
  {
    "seating_no": 1776186,
    "arabic_name": "تقى محمد فتح الله عبد الحفيظ",
    "total_degree": 221.5
  },
  {
    "seating_no": 1776187,
    "arabic_name": "تقى محمد محمود مرسى",
    "total_degree": 195.5
  },
  {
    "seating_no": 1778102,
    "arabic_name": "تقى محمد احمد السيد احمد",
    "total_degree": 202.5
  },
  {
    "seating_no": 1778272,
    "arabic_name": "تقى احمد على حسن سيد",
    "total_degree": 234
  },
  {
    "seating_no": 1780996,
    "arabic_name": "تقي عصام الدين محمد فهمى",
    "total_degree": 110
  },
  {
    "seating_no": 1781303,
    "arabic_name": "تقوى خلف فتحى محمد",
    "total_degree": 191.5
  },
  {
    "seating_no": 1782534,
    "arabic_name": "تقا المعتز فتحى حسن",
    "total_degree": 159
  },
  {
    "seating_no": 1782637,
    "arabic_name": "تقى عادل عبد الهادى عبدالله",
    "total_degree": 158.5
  },
  {
    "seating_no": 1782687,
    "arabic_name": "تقوى محمد صبرى محمود",
    "total_degree": 156.5
  },
  {
    "seating_no": 1784733,
    "arabic_name": "تقى محمود عبد الرحمن محمد",
    "total_degree": 148.5
  },
  {
    "seating_no": 1785268,
    "arabic_name": "تقى مصطفى عيد رمضان",
    "total_degree": 266
  },
  {
    "seating_no": 1789484,
    "arabic_name": "تقوى رضا السيد محمود",
    "total_degree": 258
  },
  {
    "seating_no": 1795055,
    "arabic_name": "تقى رضا أحمد محمد",
    "total_degree": 224
  },
  {
    "seating_no": 1796720,
    "arabic_name": "تقوى محمد فضل ميسر",
    "total_degree": 149.5
  },
  {
    "seating_no": 1797167,
    "arabic_name": "تقوى علاء عبد اللطيف خليل",
    "total_degree": 198
  },
  {
    "seating_no": 1805772,
    "arabic_name": "تقا حشمت ابراهيم محمد مسلوب",
    "total_degree": 242
  },
  {
    "seating_no": 1809104,
    "arabic_name": "تقي سلطان محمد حسانين احمد",
    "total_degree": 196
  },
  {
    "seating_no": 1811671,
    "arabic_name": "تقوى اكرم حسين حميد",
    "total_degree": 228
  },
  {
    "seating_no": 1815954,
    "arabic_name": "تقا محمد ريان علي محمود",
    "total_degree": 262.5
  },
  {
    "seating_no": 1816575,
    "arabic_name": "تقا حمدان محمد محمد",
    "total_degree": 291.5
  },
  {
    "seating_no": 1817281,
    "arabic_name": "تقوى سعود محمود محمد احمد",
    "total_degree": 305
  },
  {
    "seating_no": 1819614,
    "arabic_name": "تقى على مسعود عبد المجيد",
    "total_degree": 227
  },
  {
    "seating_no": 1822487,
    "arabic_name": "تقوى الحسين محمد عبد المطلب",
    "total_degree": 244.5
  },
  {
    "seating_no": 1826468,
    "arabic_name": "تقوى احمد حسن محمد عبدالله",
    "total_degree": 244
  },
  {
    "seating_no": 1828902,
    "arabic_name": "تقى سامى محمود عبد الجواد",
    "total_degree": 216.5
  },
  {
    "seating_no": 1829390,
    "arabic_name": "تقى محمد عاشور محمد على",
    "total_degree": 146
  },
  {
    "seating_no": 1831276,
    "arabic_name": "تقوى عبد الناصر احمد محمود",
    "total_degree": 262.5
  },
  {
    "seating_no": 1832414,
    "arabic_name": "تقوى شاذلى على عبدالعظيم",
    "total_degree": 230.5
  },
  {
    "seating_no": 1835534,
    "arabic_name": "تقى ابراهيم احمد محمد",
    "total_degree": 266
  },
  {
    "seating_no": 1835704,
    "arabic_name": "تقى ابراهيم محمد ابراهيم",
    "total_degree": 219.5
  },
  {
    "seating_no": 1835732,
    "arabic_name": "تقي محمد احمد ابراهيم",
    "total_degree": 164.5
  },
  {
    "seating_no": 1835733,
    "arabic_name": "تقى محمد احمدمحمد محمد ابايزيد",
    "total_degree": 203
  },
  {
    "seating_no": 1835857,
    "arabic_name": "تقى محمد عبد الله خضير",
    "total_degree": 279.5
  },
  {
    "seating_no": 1836703,
    "arabic_name": "تقى خالد احمد انور",
    "total_degree": 240.5
  },
  {
    "seating_no": 1857887,
    "arabic_name": "تقي محمد حسين محمد",
    "total_degree": 256.5
  },
  {
    "seating_no": 1858190,
    "arabic_name": "تقى أمجد أحمد عبد الصبور",
    "total_degree": 279.5
  },
  {
    "seating_no": 1858465,
    "arabic_name": "تقى مصطفى توفيق مرزوق",
    "total_degree": 199
  },
  {
    "seating_no": 1859327,
    "arabic_name": "تقى جعفر متولى محمد",
    "total_degree": 232
  },
  {
    "seating_no": 1861423,
    "arabic_name": "تقى نائل محمود عمر",
    "total_degree": 268
  },
  {
    "seating_no": 1861657,
    "arabic_name": "تقى ايمن وهمان على",
    "total_degree": 172
  },
  {
    "seating_no": 1866810,
    "arabic_name": "تقوى علاء الدين مسلم محمد",
    "total_degree": 128
  },
  {
    "seating_no": 1866967,
    "arabic_name": "تقوى سامى نعمان عثمان",
    "total_degree": 182
  },
  {
    "seating_no": 1868439,
    "arabic_name": "تقوى محمد عبد الرازق فرغلى",
    "total_degree": 157.5
  },
  {
    "seating_no": 1869593,
    "arabic_name": "تقى عامر عبد الله محمود",
    "total_degree": 273
  },
  {
    "seating_no": 1873211,
    "arabic_name": "تقى الاتاس عبدالحميد ابوزيد",
    "total_degree": 148.5
  },
  {
    "seating_no": 1873212,
    "arabic_name": "تقى مصطفى محمود يوسف",
    "total_degree": 247.5
  },
  {
    "seating_no": 1873501,
    "arabic_name": "تقى محمد على عبدالعال",
    "total_degree": 152
  },
  {
    "seating_no": 1874045,
    "arabic_name": "تقى نبيل فتحى محمد",
    "total_degree": 266
  },
  {
    "seating_no": 1876813,
    "arabic_name": "تقى محمد حسن هريدى",
    "total_degree": 236
  },
  {
    "seating_no": 1878451,
    "arabic_name": "تقى اسامة بكر محمود",
    "total_degree": 207.5
  },
  {
    "seating_no": 1880558,
    "arabic_name": "تقى مدحت محمد ابراهيم السيد",
    "total_degree": 222.5
  },
  {
    "seating_no": 1880676,
    "arabic_name": "تقه ياسر عبد الله جيلاني عبد القادر",
    "total_degree": 246
  },
  {
    "seating_no": 1881853,
    "arabic_name": "تقوى محمد فاروق محمود",
    "total_degree": 297.5
  },
  {
    "seating_no": 1884616,
    "arabic_name": "تقى عمرو عبدالكريم اسماعيل",
    "total_degree": 218.5
  },
  {
    "seating_no": 1886487,
    "arabic_name": "تقوى السيد ثابت على",
    "total_degree": 285
  },
  {
    "seating_no": 1886562,
    "arabic_name": "تقوى عبد الناصر عبد الراضى سليمان",
    "total_degree": 210.5
  },
  {
    "seating_no": 1886563,
    "arabic_name": "تقى احمد كمال عبد العال",
    "total_degree": 220.5
  },
  {
    "seating_no": 1886876,
    "arabic_name": "تقى وسام محمد السيد",
    "total_degree": 138.5
  },
  {
    "seating_no": 1888847,
    "arabic_name": "تقى مجدي عبد العال أحمد",
    "total_degree": 300.5
  },
  {
    "seating_no": 1890464,
    "arabic_name": "تقوى حسن احمد حسانين",
    "total_degree": 233.5
  },
  {
    "seating_no": 1892003,
    "arabic_name": "تقي عبدالحفيظ خليفة عبدالفتاح",
    "total_degree": 228
  },
  {
    "seating_no": 1894421,
    "arabic_name": "تقا عبد الرحمن محمد محمد عبد المجيد",
    "total_degree": 226.5
  },
  {
    "seating_no": 1899433,
    "arabic_name": "تقى وليد عرفان احمد",
    "total_degree": 231.5
  },
  {
    "seating_no": 1901284,
    "arabic_name": "تقى محمود محمد حمدان",
    "total_degree": 277
  },
  {
    "seating_no": 1901347,
    "arabic_name": "تقى احمد حسن احمد",
    "total_degree": 292
  },
  {
    "seating_no": 1904130,
    "arabic_name": "تقوى خالد جابر محمد",
    "total_degree": 277
  },
  {
    "seating_no": 1906429,
    "arabic_name": "تقى عبد الستار عبد الفتاح محمد",
    "total_degree": 195
  },
  {
    "seating_no": 1906654,
    "arabic_name": "تقى عبد الرحيم عبد العال عبد الرحيم",
    "total_degree": 205
  },
  {
    "seating_no": 1906855,
    "arabic_name": "تقى منتصر محمود حامد",
    "total_degree": 303
  },
  {
    "seating_no": 1907423,
    "arabic_name": "تقوى عبد الناصر عبد اللطيف مصطفى",
    "total_degree": 93.5
  },
  {
    "seating_no": 1909056,
    "arabic_name": "تقوى محمد كمال السيد حسين",
    "total_degree": 163
  },
  {
    "seating_no": 1098860,
    "arabic_name": "تقى محمود جوده محمود",
    "total_degree": 205
  },
  {
    "seating_no": 1098986,
    "arabic_name": "تقى ايمن زكي عبدالسلام",
    "total_degree": 185
  },
  {
    "seating_no": 1099356,
    "arabic_name": "تقى محمود جمال صديق",
    "total_degree": 188.5
  },
  {
    "seating_no": 1102830,
    "arabic_name": "تقى تامر ابراهيم محمد حسن",
    "total_degree": 162
  },
  {
    "seating_no": 1103459,
    "arabic_name": "تقى سيد احمد على سيد",
    "total_degree": 211
  },
  {
    "seating_no": 1104241,
    "arabic_name": "تقوى عيد سيد محمود",
    "total_degree": 205.5
  },
  {
    "seating_no": 1105093,
    "arabic_name": "تقوى ياسر فتحى عبدالونيس",
    "total_degree": 223
  },
  {
    "seating_no": 1106060,
    "arabic_name": "تقوى شعبان اسماعيل احمد",
    "total_degree": 215
  },
  {
    "seating_no": 1106741,
    "arabic_name": "تقوى محمود عبدالخالق عبدالمولى",
    "total_degree": 168.5
  },
  {
    "seating_no": 1109452,
    "arabic_name": "تقوى سالم احمد خليل",
    "total_degree": 205
  },
  {
    "seating_no": 1109521,
    "arabic_name": "تقى احمد عبدالفتاح عبدالحميد",
    "total_degree": 333.5
  },
  {
    "seating_no": 1114911,
    "arabic_name": "تقى احمد احمد حامد",
    "total_degree": 213
  },
  {
    "seating_no": 1190283,
    "arabic_name": "تقى محمد الدردير عزام احمد",
    "total_degree": 223
  },
  {
    "seating_no": 1190326,
    "arabic_name": "تقي فريد فؤاد رزق",
    "total_degree": 205.5
  },
  {
    "seating_no": 1190701,
    "arabic_name": "تقى محمود منسى عبدالحميد",
    "total_degree": 156.5
  },
  {
    "seating_no": 1191454,
    "arabic_name": "تقى بهاءالدين نعمه الله نعمه الله الهنيدى",
    "total_degree": 234
  },
  {
    "seating_no": 1192315,
    "arabic_name": "تقى كمال العربى عوض الله حسين",
    "total_degree": 207
  },
  {
    "seating_no": 1193414,
    "arabic_name": "تقى احمد حسن على",
    "total_degree": 222
  },
  {
    "seating_no": 1193704,
    "arabic_name": "تقى ناجى محمد عبد القادر",
    "total_degree": 211
  },
  {
    "seating_no": 1194831,
    "arabic_name": "تقوى الله محمد ابراهيم محمد",
    "total_degree": 208
  },
  {
    "seating_no": 1195496,
    "arabic_name": "تقى عبد اللطيف الخطيب محمد وحيد",
    "total_degree": 191
  },
  {
    "seating_no": 1195497,
    "arabic_name": "تقى محمد محمد عبد اللطيف",
    "total_degree": 287.5
  },
  {
    "seating_no": 1195546,
    "arabic_name": "تقى عمرو فتحى معوض ابوشامه",
    "total_degree": 209
  },
  {
    "seating_no": 1196061,
    "arabic_name": "تقوى محمد احمد عطيه حسن",
    "total_degree": 207
  },
  {
    "seating_no": 1296882,
    "arabic_name": "تقى فيصل بيومى عبدالعليم حسين",
    "total_degree": 205
  },
  {
    "seating_no": 1296891,
    "arabic_name": "تقوى احمد شحاته عبدالمنعم",
    "total_degree": 217.5
  },
  {
    "seating_no": 1297606,
    "arabic_name": "تقى احمد محمد عبدالعزيز الجمل",
    "total_degree": 250.5
  },
  {
    "seating_no": 1297742,
    "arabic_name": "تقى احمد محمد محمد رزق",
    "total_degree": 324
  },
  {
    "seating_no": 1297861,
    "arabic_name": "تقى حمد محمد على حموده",
    "total_degree": 275
  },
  {
    "seating_no": 1297925,
    "arabic_name": "تقى هانى مولد لبيب قنديل",
    "total_degree": 348
  },
  {
    "seating_no": 1298149,
    "arabic_name": "تقى سامى اسماعيل على خضر",
    "total_degree": 238.5
  },
  {
    "seating_no": 1299519,
    "arabic_name": "تقى احمد حماية سعيد غانم",
    "total_degree": 189
  },
  {
    "seating_no": 1301336,
    "arabic_name": "تقى عبد المنعم عبد الله عبد المحسن",
    "total_degree": 163
  },
  {
    "seating_no": 1302876,
    "arabic_name": "تقى عليوه مسعد عليوه جمعه",
    "total_degree": 163
  },
  {
    "seating_no": 1390935,
    "arabic_name": "تقى محمود صلاح الدين صالح سابق",
    "total_degree": 206
  },
  {
    "seating_no": 1391008,
    "arabic_name": "تقى هاشم محمود محمد البيلى",
    "total_degree": 205
  },
  {
    "seating_no": 1391279,
    "arabic_name": "تقي ابو بكر جمال الدين رشاد",
    "total_degree": 186
  },
  {
    "seating_no": 1391333,
    "arabic_name": "تقى طه حسن محمد حسن",
    "total_degree": 216.5
  },
  {
    "seating_no": 1392264,
    "arabic_name": "تقى سيد جمال عبدالمجيد محمد ",
    "total_degree": 242.5
  },
  {
    "seating_no": 1392528,
    "arabic_name": "تقى احمد شعبان عامر بندارى",
    "total_degree": 377
  },
  {
    "seating_no": 1394215,
    "arabic_name": "تقى امير صلاح احمد محمد",
    "total_degree": 218
  },
  {
    "seating_no": 1471753,
    "arabic_name": "تقى احمد محمد محمد الجوجرى",
    "total_degree": 206
  },
  {
    "seating_no": 1471947,
    "arabic_name": "تقى احمد احمد محمود عبدالسيد",
    "total_degree": 156
  },
  {
    "seating_no": 1473833,
    "arabic_name": "تقوى مجدي سعد رحومه صميده",
    "total_degree": 153.5
  },
  {
    "seating_no": 1562979,
    "arabic_name": "تقى باسم السيد محمد",
    "total_degree": 173
  },
  {
    "seating_no": 1563062,
    "arabic_name": "تقى السيد عوض محمد مبروك",
    "total_degree": 216.5
  },
  {
    "seating_no": 1563081,
    "arabic_name": "تقى رائد محمد حسن",
    "total_degree": 196.5
  },
  {
    "seating_no": 1564046,
    "arabic_name": "تقى عامر شفيق عبد المجيد الشهاوي",
    "total_degree": 221.5
  },
  {
    "seating_no": 1568363,
    "arabic_name": "تقى عبد الفتاح محمد زهران",
    "total_degree": 243.5
  },
  {
    "seating_no": 1635158,
    "arabic_name": "تقى محمد ابراهيم جمعه حمد",
    "total_degree": 364.5
  },
  {
    "seating_no": 1635251,
    "arabic_name": "تقى عبد الحميد محمد سرحان",
    "total_degree": 297.5
  },
  {
    "seating_no": 1705723,
    "arabic_name": "تقى مصطفى محمد محمود ابو الطيب",
    "total_degree": 205
  },
  {
    "seating_no": 1770464,
    "arabic_name": "تقى اشرف محمد محمد مصطفى حموده",
    "total_degree": 326
  },
  {
    "seating_no": 1770594,
    "arabic_name": "تقى الدين ابراهيم محمد محمد حسين سالم",
    "total_degree": 355.5
  },
  {
    "seating_no": 1770745,
    "arabic_name": "تقوي محمد متولي علي عبدالله",
    "total_degree": 245
  },
  {
    "seating_no": 1841487,
    "arabic_name": "تقوى عماد الدين منصور ابوبكر",
    "total_degree": 247
  },
  {
    "seating_no": 1846507,
    "arabic_name": "تقوى يوسف محمد على",
    "total_degree": 285.5
  },
  {
    "seating_no": 1847065,
    "arabic_name": "تقوى ابو الحجاج  دسوقى على",
    "total_degree": 192
  },
  {
    "seating_no": 1849632,
    "arabic_name": "تقى محمد عبداللطيف محمد",
    "total_degree": 230.5
  },
  {
    "seating_no": 1849675,
    "arabic_name": "تقوى حامد صالح رضوان",
    "total_degree": 227.5
  },
  {
    "seating_no": 1916001,
    "arabic_name": "تقى وائل بكرى محمد",
    "total_degree": 193
  }
]