[
  {
    "seating_no": 1028641,
    "arabic_name": "ثائر تامر محسن حسين عبده",
    "total_degree": 98
  },
  {
    "seating_no": 1040894,
    "arabic_name": "ثابت محمد ثابت محمد حسن",
    "total_degree": 216
  },
  {
    "seating_no": 1059154,
    "arabic_name": "ثابت ملاك ثابت عبدالنور",
    "total_degree": 284
  },
  {
    "seating_no": 1148389,
    "arabic_name": "ثابت محمود ثابت عبد  الجواد",
    "total_degree": 181.5
  },
  {
    "seating_no": 1161793,
    "arabic_name": "ثابت محمد ثابت أحمد",
    "total_degree": 228.5
  },
  {
    "seating_no": 1208742,
    "arabic_name": "ثاؤفيليا عماد صموئيل سعد",
    "total_degree": 0
  },
  {
    "seating_no": 1232893,
    "arabic_name": "ثابت احمد ثابت انوير السيد",
    "total_degree": 134
  },
  {
    "seating_no": 1240892,
    "arabic_name": "ثاؤبستا ميلاد بطرس سعيد جرجس",
    "total_degree": 200
  },
  {
    "seating_no": 1273776,
    "arabic_name": "ثابت فرج ثابت محمود حسن",
    "total_degree": 249.5
  },
  {
    "seating_no": 1306362,
    "arabic_name": "ثابت صابر مكين ثابت",
    "total_degree": 0
  },
  {
    "seating_no": 1329265,
    "arabic_name": "ثابت احمد ثابت الصادق عثمان",
    "total_degree": 229.5
  },
  {
    "seating_no": 1446108,
    "arabic_name": "ثاؤفيلس مينا عوض الله كامل جرجس",
    "total_degree": 284.5
  },
  {
    "seating_no": 1467742,
    "arabic_name": "ثائر ممدوح راغب محمد الدربالى",
    "total_degree": 270.5
  },
  {
    "seating_no": 1545821,
    "arabic_name": "ثابت يوسف ثابت جادالله",
    "total_degree": 255
  },
  {
    "seating_no": 1551513,
    "arabic_name": "ثابت عبد الحميد ثابت عبد الحميد",
    "total_degree": 0
  },
  {
    "seating_no": 1612773,
    "arabic_name": "ثابت حماده محمد محمود عبدالغنى",
    "total_degree": 275
  },
  {
    "seating_no": 1668774,
    "arabic_name": "ثابت شاكر معوض وهبه فرج",
    "total_degree": 207.5
  },
  {
    "seating_no": 1781356,
    "arabic_name": "ثابت مجيد ثابت جرجس",
    "total_degree": 239.5
  },
  {
    "seating_no": 1783983,
    "arabic_name": "ثابت حامد ثابت صالح",
    "total_degree": 213.5
  },
  {
    "seating_no": 1797130,
    "arabic_name": "ثابت ضاحى كامل على عبد القوى",
    "total_degree": 211.5
  },
  {
    "seating_no": 1877770,
    "arabic_name": "ثابت محمد ثابت سليم",
    "total_degree": 284
  },
  {
    "seating_no": 1904702,
    "arabic_name": "ثابت عفيفي ثابت حسن",
    "total_degree": 291.5
  },
  {
    "seating_no": 1108051,
    "arabic_name": "ثابت محمد قرنى ابوالعطا",
    "total_degree": 188.5
  }
]