[
  {
    "seating_no": 1073000,
    "arabic_name": "زياد عادل حسين خليفه محمد",
    "total_degree": 269
  },
  {
    "seating_no": 1073001,
    "arabic_name": "زياد فرج عبدالجيد على محمد",
    "total_degree": 147.5
  },
  {
    "seating_no": 1073002,
    "arabic_name": "زياد محمد محمود رياض",
    "total_degree": 169
  },
  {
    "seating_no": 1073003,
    "arabic_name": "زياد ياسر على معبد",
    "total_degree": 150.5
  },
  {
    "seating_no": 1073004,
    "arabic_name": "شادى معتز عبدالحميد ابراهيم",
    "total_degree": 185
  },
  {
    "seating_no": 1073005,
    "arabic_name": "طه عماد طاها عبدالله جوده",
    "total_degree": 154.5
  },
  {
    "seating_no": 1073006,
    "arabic_name": "عبدالرحمن عمرو محمد عزيز",
    "total_degree": 141.5
  },
  {
    "seating_no": 1073007,
    "arabic_name": "عصام ياسر احمد سنوسي",
    "total_degree": 131
  },
  {
    "seating_no": 1073008,
    "arabic_name": "على محمد درباله محمد",
    "total_degree": 181
  },
  {
    "seating_no": 1073009,
    "arabic_name": "عمرو موسى على عبدالمقصود على",
    "total_degree": 132.5
  },
  {
    "seating_no": 1073010,
    "arabic_name": "كريم احمد صبرى ابوبكر",
    "total_degree": 130.5
  },
  {
    "seating_no": 1073011,
    "arabic_name": "محمد احمد شعبان احمد",
    "total_degree": 114.5
  },
  {
    "seating_no": 1073012,
    "arabic_name": "محمد احمد محمد ابراهيم السيد",
    "total_degree": 209.5
  },
  {
    "seating_no": 1073013,
    "arabic_name": "محمد السيد عبدالرحمن هيكل",
    "total_degree": 119
  },
  {
    "seating_no": 1073014,
    "arabic_name": "محمد حسين كامل محمد",
    "total_degree": 132
  },
  {
    "seating_no": 1073015,
    "arabic_name": "محمد شعبان احمد عبدالباقي",
    "total_degree": 139.5
  },
  {
    "seating_no": 1073016,
    "arabic_name": "محمد صبحى عبدالحميد متولى",
    "total_degree": 84
  },
  {
    "seating_no": 1073017,
    "arabic_name": "محمد عاطف عبدالعزيز جوده",
    "total_degree": 151
  },
  {
    "seating_no": 1073018,
    "arabic_name": "محمد عاطف محمد يوسف",
    "total_degree": 111
  },
  {
    "seating_no": 1073019,
    "arabic_name": "محمد محمد زكى محمد",
    "total_degree": 173.5
  },
  {
    "seating_no": 1073020,
    "arabic_name": "محمد محمود محمد محمد",
    "total_degree": 140.5
  },
  {
    "seating_no": 1073021,
    "arabic_name": "احمد السيد محمود صادق",
    "total_degree": 270
  },
  {
    "seating_no": 1073022,
    "arabic_name": "احمد سعد سيد عبدالجواد",
    "total_degree": 103
  },
  {
    "seating_no": 1073023,
    "arabic_name": "احمد عبدالحميد احمد جاب الله",
    "total_degree": 97
  },
  {
    "seating_no": 1073024,
    "arabic_name": "احمد يونس محمد ابراهيم",
    "total_degree": 118
  },
  {
    "seating_no": 1073025,
    "arabic_name": "امير محمد محمود بريك الشاعت",
    "total_degree": 125
  },
  {
    "seating_no": 1073026,
    "arabic_name": "حامد خالد مصطفى عبدالله",
    "total_degree": 148.5
  },
  {
    "seating_no": 1073027,
    "arabic_name": "عبدالرحمن صفوت ربيع محمد",
    "total_degree": 46
  },
  {
    "seating_no": 1073028,
    "arabic_name": "عبدالرحمن صلاح محمد حسين",
    "total_degree": 107
  },
  {
    "seating_no": 1073029,
    "arabic_name": "عبدالرحمن على رياض حسن",
    "total_degree": 61
  },
  {
    "seating_no": 1073030,
    "arabic_name": "عبدالرحمن نجيب احمد عبدالحميد",
    "total_degree": 130.5
  },
  {
    "seating_no": 1073031,
    "arabic_name": "عمرو خالد محمود حسين",
    "total_degree": 120.5
  },
  {
    "seating_no": 1073032,
    "arabic_name": "محمد حسن عبدالعزيز ابراهيم",
    "total_degree": 0
  },
  {
    "seating_no": 1073033,
    "arabic_name": "محمد مراد موسى عبدالرحمن",
    "total_degree": 131
  },
  {
    "seating_no": 1073034,
    "arabic_name": "محمود جابر مفتاح السيد",
    "total_degree": 30
  },
  {
    "seating_no": 1073035,
    "arabic_name": "محمود حمدى على زيدان",
    "total_degree": 104
  },
  {
    "seating_no": 1073036,
    "arabic_name": "محمد معتز محمد اسماعيل",
    "total_degree": 197
  },
  {
    "seating_no": 1073037,
    "arabic_name": "محمود خالد حامد السيد حسن",
    "total_degree": 105.5
  },
  {
    "seating_no": 1073038,
    "arabic_name": "مصطفى جمال على محمد سلام",
    "total_degree": 146.5
  },
  {
    "seating_no": 1073039,
    "arabic_name": "هانى عماد عبدالفتاح محمد يوسف",
    "total_degree": 148
  },
  {
    "seating_no": 1073040,
    "arabic_name": "يوسف السيد عبدالعال محمد هلال",
    "total_degree": 159.5
  },
  {
    "seating_no": 1073041,
    "arabic_name": "يوسف حسين سيد سالم",
    "total_degree": 167.5
  },
  {
    "seating_no": 1073042,
    "arabic_name": "يوسف سيد عبدالمجيد مرتاح",
    "total_degree": 123.5
  },
  {
    "seating_no": 1073043,
    "arabic_name": "ابراهيم محمد احمد مفتاح محمد",
    "total_degree": 168.5
  },
  {
    "seating_no": 1073044,
    "arabic_name": "مصطفى رضوان على عبدالحميد",
    "total_degree": 262.5
  },
  {
    "seating_no": 1073045,
    "arabic_name": "عبدالله احمد مرسي عبدالباري",
    "total_degree": 130.5
  },
  {
    "seating_no": 1073140,
    "arabic_name": "اخلاص محمود مصطفي كامل",
    "total_degree": 98
  },
  {
    "seating_no": 1073141,
    "arabic_name": "اسراء احمد عيد فتحى حسن",
    "total_degree": 81
  },
  {
    "seating_no": 1073142,
    "arabic_name": "اسراء رمضان عبدالرحمن عبدالله حميده",
    "total_degree": 102
  },
  {
    "seating_no": 1073143,
    "arabic_name": "اسراء عبدالمنعم محمد عبدالمنعم",
    "total_degree": 172.5
  },
  {
    "seating_no": 1073144,
    "arabic_name": "اسماء البدرى شعبان ناصر",
    "total_degree": 123
  },
  {
    "seating_no": 1073145,
    "arabic_name": "امل السيد مصطفى احمد سليمان",
    "total_degree": 139.5
  },
  {
    "seating_no": 1073146,
    "arabic_name": "امنيه ماهر توفيق صديق",
    "total_degree": 131
  },
  {
    "seating_no": 1073147,
    "arabic_name": "اميره احمد خلف على",
    "total_degree": 126
  },
  {
    "seating_no": 1073148,
    "arabic_name": "اميره محمد كامل فاوي سيد احمد",
    "total_degree": 129.5
  },
  {
    "seating_no": 1073149,
    "arabic_name": "انجى ممدوح محمد عبدالعظيم",
    "total_degree": 182
  },
  {
    "seating_no": 1073150,
    "arabic_name": "ايات حمدى عبدالستار عبدالكريم",
    "total_degree": 168
  },
  {
    "seating_no": 1073151,
    "arabic_name": "بسمله شريف شوبك عبدالمولى",
    "total_degree": 130
  },
  {
    "seating_no": 1073152,
    "arabic_name": "بسمله محمد عبدالمنعم حسين",
    "total_degree": 104
  },
  {
    "seating_no": 1073153,
    "arabic_name": "بسمله محمد محمود سلومه خليفه",
    "total_degree": 202
  },
  {
    "seating_no": 1073154,
    "arabic_name": "بسمه عادل بدوي احمد",
    "total_degree": 196.5
  },
  {
    "seating_no": 1073155,
    "arabic_name": "بشاير رجب محمد حميده حموده",
    "total_degree": 174
  },
  {
    "seating_no": 1073156,
    "arabic_name": "تقوى شعبان محمد يوسف",
    "total_degree": 175
  },
  {
    "seating_no": 1073157,
    "arabic_name": "جنه رمضان عبدالله عبدالسميع",
    "total_degree": 96.5
  },
  {
    "seating_no": 1073158,
    "arabic_name": "جنه مصطفى عبدالحميد عبدالحليم",
    "total_degree": 136.5
  },
  {
    "seating_no": 1073159,
    "arabic_name": "حبيبه السيد راتب امين",
    "total_degree": 78.5
  },
  {
    "seating_no": 1073160,
    "arabic_name": "حبيبه سيف النصر عجمى",
    "total_degree": 132
  },
  {
    "seating_no": 1073161,
    "arabic_name": "حبيبه عزت ابراهيم محمد",
    "total_degree": 109.5
  },
  {
    "seating_no": 1073162,
    "arabic_name": "حسناء ابراهيم يس سليم",
    "total_degree": 123
  },
  {
    "seating_no": 1073163,
    "arabic_name": "خلود اسماعيل ربيع فراج",
    "total_degree": 185.5
  },
  {
    "seating_no": 1073164,
    "arabic_name": "داليا اسماعيل على اسماعيل",
    "total_degree": 82
  },
  {
    "seating_no": 1073165,
    "arabic_name": "دينا ماهر عبدالسميع عبدالرحمن",
    "total_degree": 163
  },
  {
    "seating_no": 1073166,
    "arabic_name": "رحمه ابوركاب عبدالله على",
    "total_degree": 194.5
  },
  {
    "seating_no": 1073167,
    "arabic_name": "رحمه عشرى مصطفى عبدالحليم مرسى",
    "total_degree": 136
  },
  {
    "seating_no": 1073168,
    "arabic_name": "رحمه محمد مصطفى عبدالوهاب",
    "total_degree": 76
  },
  {
    "seating_no": 1073169,
    "arabic_name": "رغده خالد على محفوظ",
    "total_degree": 102
  },
  {
    "seating_no": 1073170,
    "arabic_name": "ريم احمد عبدالقادر كليب سعداوى",
    "total_degree": 115.5
  },
  {
    "seating_no": 1073171,
    "arabic_name": "ريم عطيه عوض عبدالعاطى",
    "total_degree": 188
  },
  {
    "seating_no": 1073172,
    "arabic_name": "ريهام رجب ايوب محمد",
    "total_degree": 141
  },
  {
    "seating_no": 1073173,
    "arabic_name": "ريهام محمود حسين محمد",
    "total_degree": 106.5
  },
  {
    "seating_no": 1073174,
    "arabic_name": "زينب احمد محمد فرنوي",
    "total_degree": 242
  },
  {
    "seating_no": 1073175,
    "arabic_name": "سميه محمد حمزاوى عبداللطيف",
    "total_degree": 129.5
  },
  {
    "seating_no": 1073176,
    "arabic_name": "سوزان حسن عبيد حسن",
    "total_degree": 199
  },
  {
    "seating_no": 1073177,
    "arabic_name": "شروق ممدوح السيد محمد عبدالجليل",
    "total_degree": 188.5
  },
  {
    "seating_no": 1073178,
    "arabic_name": "شهد احمد محمد احمد",
    "total_degree": 99
  },
  {
    "seating_no": 1073179,
    "arabic_name": "شهد سعيد محمد سعيد محمد",
    "total_degree": 178
  },
  {
    "seating_no": 1073180,
    "arabic_name": "شهد عيد محمد عبدالرازق",
    "total_degree": 95
  },
  {
    "seating_no": 1073181,
    "arabic_name": "شيماء شعبان عبدالرحمن رزق",
    "total_degree": 143
  },
  {
    "seating_no": 1073182,
    "arabic_name": "صابرين اشرف سعد محمد",
    "total_degree": 146
  },
  {
    "seating_no": 1073183,
    "arabic_name": "صفا عبدالسلام عبدالعاطى عبدالغنى عطيه",
    "total_degree": 161
  },
  {
    "seating_no": 1073184,
    "arabic_name": "عفاف عبدالمقصود عبدالله عبدالمقصود",
    "total_degree": 117
  },
  {
    "seating_no": 1073185,
    "arabic_name": "عواطف جلال الدين السيد عبدالحميد",
    "total_degree": 147.5
  },
  {
    "seating_no": 1073186,
    "arabic_name": "فاتن عبدالسلام محمد عوض",
    "total_degree": 178.5
  },
  {
    "seating_no": 1073187,
    "arabic_name": "فاطمه رمضان على عبدالتواب",
    "total_degree": 114
  },
  {
    "seating_no": 1073188,
    "arabic_name": "فاطمه شعبان احمد عبدالباقي",
    "total_degree": 198
  },
  {
    "seating_no": 1073189,
    "arabic_name": "فاطمه مصطفى فتحى محمد",
    "total_degree": 188.5
  },
  {
    "seating_no": 1073190,
    "arabic_name": "لبنى عيد عبدالعزيز محمود",
    "total_degree": 107
  },
  {
    "seating_no": 1073191,
    "arabic_name": "لجين احمد جلال الدين احمد جوده",
    "total_degree": 149
  },
  {
    "seating_no": 1073192,
    "arabic_name": "مروه نادى عبدالونيس علوانى",
    "total_degree": 138
  },
  {
    "seating_no": 1073193,
    "arabic_name": "مريم احمد محمد كمال",
    "total_degree": 178.5
  },
  {
    "seating_no": 1073194,
    "arabic_name": "مريم على صلاح احمد محمد شلبي",
    "total_degree": 191.5
  },
  {
    "seating_no": 1073195,
    "arabic_name": "مريم على محمود محمد محمد",
    "total_degree": 112
  },
  {
    "seating_no": 1073196,
    "arabic_name": "ملك حجاج على عبدالرحمن حسان",
    "total_degree": 120.5
  },
  {
    "seating_no": 1073197,
    "arabic_name": "منار محمد عبدالعزيز عبدالواحد",
    "total_degree": 175
  },
  {
    "seating_no": 1073198,
    "arabic_name": "منه الله انور كمال كامل",
    "total_degree": 140
  },
  {
    "seating_no": 1073199,
    "arabic_name": "منه الله على زكى محمد",
    "total_degree": 161
  },
  {
    "seating_no": 1073200,
    "arabic_name": "منه الله محمود فارس احمد",
    "total_degree": 148.5
  },
  {
    "seating_no": 1073201,
    "arabic_name": "منه خالد محمود توفيق احمد",
    "total_degree": 198
  },
  {
    "seating_no": 1073202,
    "arabic_name": "منى روبى السيد علي ابراهيم",
    "total_degree": 155
  },
  {
    "seating_no": 1073203,
    "arabic_name": "مى احمد مجدي عبدالرحمن",
    "total_degree": 156.5
  },
  {
    "seating_no": 1073204,
    "arabic_name": "مى عبدالرحمن جعفر عبدالرحمن",
    "total_degree": 137
  },
  {
    "seating_no": 1073205,
    "arabic_name": "نجوي رمضان علي عبدالتواب قطب",
    "total_degree": 104
  },
  {
    "seating_no": 1073206,
    "arabic_name": "ندا عيد السيد منصور",
    "total_degree": 170
  },
  {
    "seating_no": 1073207,
    "arabic_name": "نرمين محمد عبدالله محمد عوض",
    "total_degree": 61
  },
  {
    "seating_no": 1073208,
    "arabic_name": "نعمه هاشم عوض الله عبدالرازق السيد",
    "total_degree": 158
  },
  {
    "seating_no": 1073209,
    "arabic_name": "نورا عبدالونيس ابوبكر عبدالله",
    "total_degree": 175.5
  },
  {
    "seating_no": 1073210,
    "arabic_name": "نورا محمد على دكرورى عيد",
    "total_degree": 185.5
  },
  {
    "seating_no": 1073211,
    "arabic_name": "نورهان عطوه ابوالنور عطوه",
    "total_degree": 121.5
  },
  {
    "seating_no": 1073212,
    "arabic_name": "هاجر احمد رشاد توفيق",
    "total_degree": 151.5
  },
  {
    "seating_no": 1073213,
    "arabic_name": "هاجر السيد مصطفي محمد سيف النصر",
    "total_degree": 240.5
  },
  {
    "seating_no": 1073214,
    "arabic_name": "هاجر صايم شحات عبدالحميد",
    "total_degree": 106
  },
  {
    "seating_no": 1073215,
    "arabic_name": "هبه على امين مرسى",
    "total_degree": 125
  },
  {
    "seating_no": 1073216,
    "arabic_name": "هدى السيد محمد عبدالفضيل",
    "total_degree": 146
  },
  {
    "seating_no": 1073217,
    "arabic_name": "هند شعبان حامد محمد",
    "total_degree": 200
  },
  {
    "seating_no": 1073218,
    "arabic_name": "ياره فرج حسين فرج",
    "total_degree": 164
  },
  {
    "seating_no": 1073219,
    "arabic_name": "ياسمين رشدى فتحى حامد",
    "total_degree": 217
  },
  {
    "seating_no": 1073220,
    "arabic_name": "ياسمين محمد رشاد توفيق",
    "total_degree": 101
  },
  {
    "seating_no": 1073221,
    "arabic_name": "يمنى حسين سيد حسين",
    "total_degree": 165
  },
  {
    "seating_no": 1073222,
    "arabic_name": "اسراء عبدالعال عثمان يونس",
    "total_degree": 158
  },
  {
    "seating_no": 1073223,
    "arabic_name": "اميره محمد توفيق عبدالرحمن",
    "total_degree": 105.5
  },
  {
    "seating_no": 1073224,
    "arabic_name": "انتصار احمد السيد عبدالجواد",
    "total_degree": 121
  },
  {
    "seating_no": 1073225,
    "arabic_name": "جنا شعبان حافظ عبدالسميع",
    "total_degree": 104
  },
  {
    "seating_no": 1073226,
    "arabic_name": "حبيبه معوض عيد عبدالفتاح",
    "total_degree": 190.5
  },
  {
    "seating_no": 1073227,
    "arabic_name": "خلود عبدالجواد مصطفى عبدالجواد",
    "total_degree": 143
  },
  {
    "seating_no": 1073228,
    "arabic_name": "دينا بهجت خميس حافظ",
    "total_degree": 122.5
  },
  {
    "seating_no": 1073229,
    "arabic_name": "رحمه عبدالله شعبان عبدالمهدى",
    "total_degree": 99
  },
  {
    "seating_no": 1073230,
    "arabic_name": "روان محمد احمد مرزوق مجاهد",
    "total_degree": 108
  },
  {
    "seating_no": 1073231,
    "arabic_name": "زينات مجدى سلامه عبدالعزيز مصطفى",
    "total_degree": 92
  },
  {
    "seating_no": 1073232,
    "arabic_name": "ساره السيد على السيد",
    "total_degree": 214.5
  },
  {
    "seating_no": 1073233,
    "arabic_name": "ساره محمود احمد قطب",
    "total_degree": 82.5
  },
  {
    "seating_no": 1073234,
    "arabic_name": "سحر محمد عبد الحليم ابراهيم",
    "total_degree": 92
  },
  {
    "seating_no": 1073235,
    "arabic_name": "سهيله فرحات سنوسى عبدالرحمن",
    "total_degree": 98
  },
  {
    "seating_no": 1073236,
    "arabic_name": "شروق هشام محمد السيد",
    "total_degree": 191
  },
  {
    "seating_no": 1073237,
    "arabic_name": "شهد حسن ربيع اسماعيل",
    "total_degree": 98
  },
  {
    "seating_no": 1073238,
    "arabic_name": "شهد رجب رمضان محمود",
    "total_degree": 77
  },
  {
    "seating_no": 1073239,
    "arabic_name": "شهد رمضان عبدالفتاح احمد",
    "total_degree": 94.5
  },
  {
    "seating_no": 1073240,
    "arabic_name": "شهد عمر ابراهيم احمد",
    "total_degree": 172.5
  },
  {
    "seating_no": 1073241,
    "arabic_name": "شهد محمود عبدالعظيم علي",
    "total_degree": 133
  },
  {
    "seating_no": 1073242,
    "arabic_name": "شهد هاشم محمد عبدالله مرسي",
    "total_degree": 156.5
  },
  {
    "seating_no": 1073243,
    "arabic_name": "شيماء خالد حسنى عبدالمعز",
    "total_degree": 129
  },
  {
    "seating_no": 1073244,
    "arabic_name": "صفيه عيد جنيدى معوض",
    "total_degree": 159.5
  },
  {
    "seating_no": 1073245,
    "arabic_name": "ضحي محمد موسي هديب",
    "total_degree": 278
  },
  {
    "seating_no": 1073246,
    "arabic_name": "علا خليفه كليب عبدالحميد حسان",
    "total_degree": 131
  },
  {
    "seating_no": 1073247,
    "arabic_name": "علياء علي عبدالمولي محمد",
    "total_degree": 84
  },
  {
    "seating_no": 1073248,
    "arabic_name": "فاطمه ايمن محمد عبدالسلام",
    "total_degree": 121
  },
  {
    "seating_no": 1073249,
    "arabic_name": "فاطمه على ابوالحسب هديب",
    "total_degree": 171
  },
  {
    "seating_no": 1073250,
    "arabic_name": "مريم محمد السيد احمد حسانين",
    "total_degree": 111
  },
  {
    "seating_no": 1073251,
    "arabic_name": "مريم مصطفي الصوفي بكري",
    "total_degree": 111
  },
  {
    "seating_no": 1073252,
    "arabic_name": "منار محمود احمد عباس",
    "total_degree": 174.5
  },
  {
    "seating_no": 1073253,
    "arabic_name": "منه الله عادل ورداني خميس",
    "total_degree": 83
  },
  {
    "seating_no": 1073254,
    "arabic_name": "منه الله ناصر هاشم محمود",
    "total_degree": 105
  },
  {
    "seating_no": 1073255,
    "arabic_name": "نشوى عبدالتواب ابراهيم عبدالرحمن",
    "total_degree": 160.5
  },
  {
    "seating_no": 1073256,
    "arabic_name": "نعمه رجب محمد عبدالعليم",
    "total_degree": 113.5
  },
  {
    "seating_no": 1073257,
    "arabic_name": "هبه محمد علي هاشم",
    "total_degree": 129.5
  },
  {
    "seating_no": 1073258,
    "arabic_name": "هدى علاء عبدالله على",
    "total_degree": 133.5
  },
  {
    "seating_no": 1073259,
    "arabic_name": "هند عبدالفتاح عيد حموده",
    "total_degree": 111
  },
  {
    "seating_no": 1073260,
    "arabic_name": "امنه عطيه عبدالغنى عبدالفتاح",
    "total_degree": 121.5
  },
  {
    "seating_no": 1073261,
    "arabic_name": "حبيبه عطيه عويس السيد",
    "total_degree": 157
  },
  {
    "seating_no": 1073350,
    "arabic_name": "ابرام كرم نصرالله وهيب نصرالله",
    "total_degree": 230.5
  },
  {
    "seating_no": 1073351,
    "arabic_name": "احمد حماده محمد عبدالظاهر",
    "total_degree": 264
  },
  {
    "seating_no": 1073352,
    "arabic_name": "احمد محمد عبدالعليم عمار",
    "total_degree": 292
  },
  {
    "seating_no": 1073353,
    "arabic_name": "ادم خالد محمد عبدالوهاب",
    "total_degree": 289.5
  },
  {
    "seating_no": 1073354,
    "arabic_name": "انس نادى عبدالعظيم ابراهيم",
    "total_degree": 276.5
  },
  {
    "seating_no": 1073355,
    "arabic_name": "ايمن عبدالسلام جاب الله سالم",
    "total_degree": 233
  },
  {
    "seating_no": 1073356,
    "arabic_name": "بشير جبران بشير على",
    "total_degree": 264.5
  },
  {
    "seating_no": 1073357,
    "arabic_name": "خالد محمد عبدالسلام محمد",
    "total_degree": 175
  },
  {
    "seating_no": 1073358,
    "arabic_name": "طارق سيد محمود عبدالرازق",
    "total_degree": 183
  },
  {
    "seating_no": 1073359,
    "arabic_name": "عبدالحميد عادل عبدالحميد عبدالباقى",
    "total_degree": 182.5
  },
  {
    "seating_no": 1073360,
    "arabic_name": "عبدالرحمن ابراهيم سيد ابراهيم",
    "total_degree": 261.5
  },
  {
    "seating_no": 1073361,
    "arabic_name": "عمر احمد صلاح محمد",
    "total_degree": 220.5
  },
  {
    "seating_no": 1073362,
    "arabic_name": "عمر سعد احمد جمعه",
    "total_degree": 201
  },
  {
    "seating_no": 1073363,
    "arabic_name": "عمر محمد خليفه حميده",
    "total_degree": 136
  },
  {
    "seating_no": 1073364,
    "arabic_name": "عمرو جمال معنى عبدالرازق",
    "total_degree": 210
  },
  {
    "seating_no": 1073365,
    "arabic_name": "فارس درباله عبدالتواب عبدالغنى",
    "total_degree": 243.5
  },
  {
    "seating_no": 1073366,
    "arabic_name": "فاضل محمد فاضل صادق",
    "total_degree": 223
  },
  {
    "seating_no": 1073367,
    "arabic_name": "محمد احمد عبدالرؤف احمد",
    "total_degree": 213.5
  },
  {
    "seating_no": 1073368,
    "arabic_name": "محمد احمد محمد احمد معوض",
    "total_degree": 224.5
  },
  {
    "seating_no": 1073369,
    "arabic_name": "محمد حامد عبدالرحمن محمد السيد",
    "total_degree": 275.5
  },
  {
    "seating_no": 1073370,
    "arabic_name": "محمد حمدى السيد فتح الباب",
    "total_degree": 243.5
  },
  {
    "seating_no": 1073371,
    "arabic_name": "محمد طلب عبدالمنعم طلب",
    "total_degree": 203
  },
  {
    "seating_no": 1073372,
    "arabic_name": "محمد عماد عبدالظاهر مجاهد طلبه",
    "total_degree": 219
  },
  {
    "seating_no": 1073373,
    "arabic_name": "محمد عمر عدلى عبدالمولى",
    "total_degree": 199.5
  },
  {
    "seating_no": 1073374,
    "arabic_name": "محمد ناصر ربيع احمد",
    "total_degree": 246.5
  },
  {
    "seating_no": 1073375,
    "arabic_name": "محمد ناصر فوزى محمد",
    "total_degree": 233.5
  },
  {
    "seating_no": 1073376,
    "arabic_name": "محمود خالد محمد محمد السيد",
    "total_degree": 221
  },
  {
    "seating_no": 1073377,
    "arabic_name": "محمود عادل عبدالفتاح محمود",
    "total_degree": 261
  },
  {
    "seating_no": 1073378,
    "arabic_name": "مصطفى شعبان عبدالتواب عبدالصادق",
    "total_degree": 200.5
  },
  {
    "seating_no": 1073379,
    "arabic_name": "ممدوح عزت فرحات ابالى عبدالسيد",
    "total_degree": 217
  },
  {
    "seating_no": 1073380,
    "arabic_name": "هشام علاءالدين مصطفى جبريل",
    "total_degree": 238
  },
  {
    "seating_no": 1073381,
    "arabic_name": "يحى احمد احمد على محفوظ",
    "total_degree": 268
  },
  {
    "seating_no": 1073382,
    "arabic_name": "يوسف رمضان ميلاد صالح",
    "total_degree": 233.5
  },
  {
    "seating_no": 1073383,
    "arabic_name": "يوسف عبدالسلام عبدالستار جوده عيد",
    "total_degree": 242.5
  },
  {
    "seating_no": 1073384,
    "arabic_name": "ابراهيم خالد ابراهيم السيد",
    "total_degree": 192
  },
  {
    "seating_no": 1073385,
    "arabic_name": "ابراهيم محمود احمد هوارى",
    "total_degree": 194
  },
  {
    "seating_no": 1073386,
    "arabic_name": "احمد اشرف جمعه امين",
    "total_degree": 171
  },
  {
    "seating_no": 1073387,
    "arabic_name": "احمد اشرف سيد حسن",
    "total_degree": 198
  },
  {
    "seating_no": 1073388,
    "arabic_name": "احمد اشرف عبدالسلام محمد",
    "total_degree": 260.5
  },
  {
    "seating_no": 1073389,
    "arabic_name": "احمد باهى احمد عبدالظاهر",
    "total_degree": 235
  },
  {
    "seating_no": 1073390,
    "arabic_name": "احمد بدوى احمد على عبدالفتاح",
    "total_degree": 250
  },
  {
    "seating_no": 1073391,
    "arabic_name": "احمد جمال عبدالتواب عبدالعليم",
    "total_degree": 260
  },
  {
    "seating_no": 1073392,
    "arabic_name": "احمد حسين احمد اسماعيل طلبه",
    "total_degree": 299
  },
  {
    "seating_no": 1073393,
    "arabic_name": "احمد حسين صالح محمد زيدان",
    "total_degree": 266.5
  },
  {
    "seating_no": 1073394,
    "arabic_name": "احمد حمدى عبدالحميد محمد عبدالحميد",
    "total_degree": 212
  },
  {
    "seating_no": 1073395,
    "arabic_name": "احمد حمدى على عبدالهادى",
    "total_degree": 206.5
  },
  {
    "seating_no": 1073396,
    "arabic_name": "احمد ربيع عبدالتواب عبدالسلام",
    "total_degree": 206.5
  },
  {
    "seating_no": 1073397,
    "arabic_name": "احمد ربيع على احمد",
    "total_degree": 273
  },
  {
    "seating_no": 1073398,
    "arabic_name": "احمد ربيع محمد على",
    "total_degree": 177
  },
  {
    "seating_no": 1073399,
    "arabic_name": "احمد ربيع محمود عبدالنبى",
    "total_degree": 177
  },
  {
    "seating_no": 1073400,
    "arabic_name": "احمد رمضان ربيع جاد",
    "total_degree": 210
  },
  {
    "seating_no": 1073401,
    "arabic_name": "احمد رمضان كامل هلال مرسى",
    "total_degree": 191
  },
  {
    "seating_no": 1073402,
    "arabic_name": "احمد سالم احمد محمد عويس",
    "total_degree": 253.5
  },
  {
    "seating_no": 1073403,
    "arabic_name": "احمد سعد ابراهيم السيد",
    "total_degree": 271.5
  },
  {
    "seating_no": 1073404,
    "arabic_name": "احمد شعبان السيد عبدالجواد",
    "total_degree": 165
  },
  {
    "seating_no": 1073405,
    "arabic_name": "احمد عادل عبدالعظيم رجب قطب",
    "total_degree": 146.5
  },
  {
    "seating_no": 1073406,
    "arabic_name": "احمد عادل عبدالوهاب صالح",
    "total_degree": 127
  },
  {
    "seating_no": 1073407,
    "arabic_name": "احمد عبدالتواب خميس حسن",
    "total_degree": 271.5
  },
  {
    "seating_no": 1073408,
    "arabic_name": "احمد عبدالسلام عبدالله عبدالعليم",
    "total_degree": 196.5
  },
  {
    "seating_no": 1073409,
    "arabic_name": "احمد عبدالمعز عبدالحميد عبدالمحسن",
    "total_degree": 201
  },
  {
    "seating_no": 1073410,
    "arabic_name": "احمد علاءالدين عبدالله قرنى",
    "total_degree": 207.5
  },
  {
    "seating_no": 1073411,
    "arabic_name": "احمد على احمد رجب",
    "total_degree": 154
  },
  {
    "seating_no": 1073412,
    "arabic_name": "احمد على عبدالهادى عبدالعزيز",
    "total_degree": 204
  },
  {
    "seating_no": 1073413,
    "arabic_name": "احمد عماد عبدالحليم منصور",
    "total_degree": 165.5
  },
  {
    "seating_no": 1073414,
    "arabic_name": "احمد عمر محمد وفيق",
    "total_degree": 147.5
  },
  {
    "seating_no": 1073415,
    "arabic_name": "احمد كمال منصور فرج",
    "total_degree": 251.5
  },
  {
    "seating_no": 1073416,
    "arabic_name": "احمد محمد حسين حسين مبارك",
    "total_degree": 183.5
  },
  {
    "seating_no": 1073417,
    "arabic_name": "احمد محمد عبدالله طنطاوى",
    "total_degree": 279.5
  },
  {
    "seating_no": 1073418,
    "arabic_name": "احمد محمد عطاء امين",
    "total_degree": 169
  },
  {
    "seating_no": 1073419,
    "arabic_name": "احمد منصور فرج عبدالحميد",
    "total_degree": 235.5
  },
  {
    "seating_no": 1073420,
    "arabic_name": "احمد ناصر عبدالفتاح رياض",
    "total_degree": 241
  },
  {
    "seating_no": 1073421,
    "arabic_name": "احمد نورالدين محمد محمد محمد",
    "total_degree": 247
  },
  {
    "seating_no": 1073422,
    "arabic_name": "اسامه احمد عبدالفتاح هاشم السيد",
    "total_degree": 268.5
  },
  {
    "seating_no": 1073423,
    "arabic_name": "اسامه ربيع شعبان محمد",
    "total_degree": 189.5
  },
  {
    "seating_no": 1073424,
    "arabic_name": "اسلام احمد محمد مصطفى",
    "total_degree": 196
  },
  {
    "seating_no": 1073425,
    "arabic_name": "اسلام محمد عبدالستار عبدالسميع",
    "total_degree": 246.5
  },
  {
    "seating_no": 1073426,
    "arabic_name": "المعتصم بالله محمد زيدان سيد عويس",
    "total_degree": 232.5
  },
  {
    "seating_no": 1073427,
    "arabic_name": "انس السيد عبدالواحد خليفه",
    "total_degree": 231
  },
  {
    "seating_no": 1073428,
    "arabic_name": "انس بدوى عبدالستار مصطفى",
    "total_degree": 214
  },
  {
    "seating_no": 1073429,
    "arabic_name": "انس رجب عبدالله طه سعيد",
    "total_degree": 244.5
  },
  {
    "seating_no": 1073430,
    "arabic_name": "انس رجب مصطفى ميزار",
    "total_degree": 278.5
  },
  {
    "seating_no": 1073431,
    "arabic_name": "انس سعد رجب مجاهد",
    "total_degree": 219.5
  },
  {
    "seating_no": 1073432,
    "arabic_name": "ايمن عبدالتواب مصطفى احمد",
    "total_degree": 292.5
  },
  {
    "seating_no": 1073433,
    "arabic_name": "ايمن محمد كمال محمد",
    "total_degree": 272
  },
  {
    "seating_no": 1073434,
    "arabic_name": "بسام محمد السيد عبدالهادى",
    "total_degree": 120
  },
  {
    "seating_no": 1073435,
    "arabic_name": "بلال محمد بى حميده",
    "total_degree": 258.5
  },
  {
    "seating_no": 1073436,
    "arabic_name": "جمال عبدالناصر عبدالسميع عبدالظاهر",
    "total_degree": 182.5
  },
  {
    "seating_no": 1073437,
    "arabic_name": "حازم طارق عبدالنبى معبدعبدالباقى",
    "total_degree": 148
  },
  {
    "seating_no": 1073438,
    "arabic_name": "حازم عبدالعليم عوض عبدالعليم",
    "total_degree": 203.5
  },
  {
    "seating_no": 1073439,
    "arabic_name": "حسام غالى احمد محمد",
    "total_degree": 264.5
  },
  {
    "seating_no": 1073440,
    "arabic_name": "حسام مصطفى رمضان عبدالرسول",
    "total_degree": 295
  },
  {
    "seating_no": 1073441,
    "arabic_name": "حسام ناصر صالح سعد",
    "total_degree": 244
  },
  {
    "seating_no": 1073442,
    "arabic_name": "خالد عبدالتواب عبدالعظيم محمد",
    "total_degree": 245
  },
  {
    "seating_no": 1073443,
    "arabic_name": "ربيع احمد امين انور",
    "total_degree": 212.5
  },
  {
    "seating_no": 1073444,
    "arabic_name": "رمضان عبدالنبى رمضان ضيف",
    "total_degree": 295
  },
  {
    "seating_no": 1073445,
    "arabic_name": "زياد احمد ابراهيم احمد",
    "total_degree": 271.5
  },
  {
    "seating_no": 1073446,
    "arabic_name": "زياد احمد على عبدالمنعم",
    "total_degree": 255
  },
  {
    "seating_no": 1073447,
    "arabic_name": "زياد احمد محمد شعبان",
    "total_degree": 183
  },
  {
    "seating_no": 1073448,
    "arabic_name": "زياد اشرف بعزق سعيد",
    "total_degree": 158.5
  },
  {
    "seating_no": 1073449,
    "arabic_name": "زياد اشرف عبدالعظيم عبدالتواب",
    "total_degree": 129
  },
  {
    "seating_no": 1073450,
    "arabic_name": "زياد اكرامى محمود معوض",
    "total_degree": 216.5
  },
  {
    "seating_no": 1073451,
    "arabic_name": "زياد حامد شعبان عبدالتواب",
    "total_degree": 260
  },
  {
    "seating_no": 1073452,
    "arabic_name": "زياد رمضان رزق محمد",
    "total_degree": 184.5
  },
  {
    "seating_no": 1073453,
    "arabic_name": "زياد عبدالظاهر فتحى عبدالظاهر",
    "total_degree": 266.5
  },
  {
    "seating_no": 1073454,
    "arabic_name": "زياد عشرى داود عبدالعزيز",
    "total_degree": 235
  },
  {
    "seating_no": 1073455,
    "arabic_name": "زياد كمال عويس قرنى عبدالعزيز",
    "total_degree": 213
  },
  {
    "seating_no": 1073456,
    "arabic_name": "زياد مؤمن عبدالله نوفل",
    "total_degree": 231
  },
  {
    "seating_no": 1073457,
    "arabic_name": "زياد محمد على محمد رجب",
    "total_degree": 239.5
  },
  {
    "seating_no": 1073458,
    "arabic_name": "زياد وائل سعد راتب",
    "total_degree": 198.5
  },
  {
    "seating_no": 1073459,
    "arabic_name": "زياد وليد السيد الصافى",
    "total_degree": 197
  },
  {
    "seating_no": 1073460,
    "arabic_name": "سامح سيد محمد محمد",
    "total_degree": 202
  },
  {
    "seating_no": 1073461,
    "arabic_name": "سفيان محمود شعبان احمد",
    "total_degree": 233.5
  },
  {
    "seating_no": 1073462,
    "arabic_name": "سليم محمد السيد جلال محمد",
    "total_degree": 263
  },
  {
    "seating_no": 1073463,
    "arabic_name": "سليم محمد سعد محمد",
    "total_degree": 257
  },
  {
    "seating_no": 1073464,
    "arabic_name": "سيد فراج حسان على",
    "total_degree": 210
  },
  {
    "seating_no": 1073465,
    "arabic_name": "سيف الدين تيسير محمود صلاح",
    "total_degree": 256.5
  },
  {
    "seating_no": 1073466,
    "arabic_name": "سيف الدين ربيع شحاته مرسى",
    "total_degree": 261.5
  },
  {
    "seating_no": 1073467,
    "arabic_name": "شادى محمد حمدى قاسم غنيم",
    "total_degree": 211.5
  },
  {
    "seating_no": 1073468,
    "arabic_name": "شهاب اشرف السيد عبدالحليم",
    "total_degree": 256.5
  },
  {
    "seating_no": 1073469,
    "arabic_name": "شهاب مجدى عبدالنبى على",
    "total_degree": 151
  },
  {
    "seating_no": 1073470,
    "arabic_name": "صلاح عصام صلاح الدين عبدالغنى",
    "total_degree": 261
  },
  {
    "seating_no": 1073471,
    "arabic_name": "طارق محمد رمضان السيد",
    "total_degree": 263
  },
  {
    "seating_no": 1073472,
    "arabic_name": "عاصم احمد عبدالتواب عبدالحليم",
    "total_degree": 209.5
  },
  {
    "seating_no": 1073473,
    "arabic_name": "عبدالرحمن السيد محمد محمد",
    "total_degree": 185.5
  },
  {
    "seating_no": 1073474,
    "arabic_name": "عبدالرحمن جمال عثمان سعيد",
    "total_degree": 240
  },
  {
    "seating_no": 1073475,
    "arabic_name": "عبدالرحمن حاتم حسين اسماعيل",
    "total_degree": 189.5
  },
  {
    "seating_no": 1073476,
    "arabic_name": "عبدالرحمن حماده يوسف رمضان",
    "total_degree": 143.5
  },
  {
    "seating_no": 1073477,
    "arabic_name": "عبدالرحمن ربيع عبدالفتاح محمد",
    "total_degree": 274
  },
  {
    "seating_no": 1073478,
    "arabic_name": "عبدالرحمن رجب عبدالله رجب",
    "total_degree": 168
  },
  {
    "seating_no": 1073479,
    "arabic_name": "عبدالرحمن رجب محمد محمد على",
    "total_degree": 225
  },
  {
    "seating_no": 1073480,
    "arabic_name": "عبدالرحمن طارق عبدالرحمن سالم",
    "total_degree": 176.5
  },
  {
    "seating_no": 1073481,
    "arabic_name": "عبدالرحمن فتحى عبدالواحد مهلهل",
    "total_degree": 194
  },
  {
    "seating_no": 1073482,
    "arabic_name": "عبدالرحمن كرم السيد عبدالفتاح",
    "total_degree": 283.5
  },
  {
    "seating_no": 1073483,
    "arabic_name": "عبدالرحمن كرم حامد عبدالمجيد",
    "total_degree": 224.5
  },
  {
    "seating_no": 1073484,
    "arabic_name": "عبدالرحمن محمد عبدالمنعم محمود",
    "total_degree": 208.5
  },
  {
    "seating_no": 1073485,
    "arabic_name": "عبدالرحمن محمود حنفى محمود",
    "total_degree": 110
  },
  {
    "seating_no": 1073486,
    "arabic_name": "عبدالرحمن ممدوح سعد عبدالرازق",
    "total_degree": 167
  },
  {
    "seating_no": 1073487,
    "arabic_name": "عبدالرحمن موسى سعيد عبدالهادى محمد",
    "total_degree": 235
  },
  {
    "seating_no": 1073488,
    "arabic_name": "عبدالرحمن هلال محمد احمد",
    "total_degree": 180
  },
  {
    "seating_no": 1073489,
    "arabic_name": "عبدالعزيز محمود حلمى محمد طنطاوى",
    "total_degree": 272.5
  },
  {
    "seating_no": 1073490,
    "arabic_name": "عبدالله احمد سعيد مصطفى",
    "total_degree": 238
  },
  {
    "seating_no": 1073491,
    "arabic_name": "عبدالله ايمن احمد جاد",
    "total_degree": 195
  },
  {
    "seating_no": 1073492,
    "arabic_name": "عبدالله بدوى محمد احمد",
    "total_degree": 254.5
  },
  {
    "seating_no": 1073493,
    "arabic_name": "عبدالله خالد سيد رمضان",
    "total_degree": 224.5
  },
  {
    "seating_no": 1073494,
    "arabic_name": "عبدالله سيد محمد ابراهيم",
    "total_degree": 297.5
  },
  {
    "seating_no": 1073495,
    "arabic_name": "عبدالله سيف سالم احمد",
    "total_degree": 241
  },
  {
    "seating_no": 1073496,
    "arabic_name": "عبدالله محمد عبدالله محمد ابراهيم",
    "total_degree": 201
  },
  {
    "seating_no": 1073497,
    "arabic_name": "عبدالمنعم محمد عبدالحميد فهمى",
    "total_degree": 171.5
  },
  {
    "seating_no": 1073498,
    "arabic_name": "على احمد على محمد",
    "total_degree": 195.5
  },
  {
    "seating_no": 1073499,
    "arabic_name": "على الدين عصام اسماعيل عبدالتواب على",
    "total_degree": 215.5
  },
  {
    "seating_no": 1073500,
    "arabic_name": "على صبرى احمد عبدالتواب",
    "total_degree": 222
  },
  {
    "seating_no": 1073501,
    "arabic_name": "على طارق على حسن",
    "total_degree": 285.5
  },
  {
    "seating_no": 1073502,
    "arabic_name": "على محمد على عبدالظاهر",
    "total_degree": 262.5
  },
  {
    "seating_no": 1073503,
    "arabic_name": "على مندى عبدالكريم عبدالعال",
    "total_degree": 247
  },
  {
    "seating_no": 1073504,
    "arabic_name": "عمار احمد عبدالله عبدالرحيم",
    "total_degree": 204
  },
  {
    "seating_no": 1073505,
    "arabic_name": "عمار علاء توبه عبدالجواد",
    "total_degree": 170
  },
  {
    "seating_no": 1073506,
    "arabic_name": "عمار محمد محمد عثمان عبدالله",
    "total_degree": 258.5
  },
  {
    "seating_no": 1073507,
    "arabic_name": "عمر احمد سيد احمد",
    "total_degree": 202
  },
  {
    "seating_no": 1073508,
    "arabic_name": "عمر اشرف شعبان حسن عبدالمجيد",
    "total_degree": 273
  },
  {
    "seating_no": 1073509,
    "arabic_name": "عمر اشرف متولى عبدالسيد احمد",
    "total_degree": 161
  },
  {
    "seating_no": 1073510,
    "arabic_name": "عمر خالد عبدالحميد فتيانى",
    "total_degree": 235
  },
  {
    "seating_no": 1073511,
    "arabic_name": "عمر شريف محمد حلمى",
    "total_degree": 217.5
  },
  {
    "seating_no": 1073512,
    "arabic_name": "عمر عادل محمد عبدالباقى",
    "total_degree": 288
  },
  {
    "seating_no": 1073513,
    "arabic_name": "عمر عماد عمر على",
    "total_degree": 252.5
  },
  {
    "seating_no": 1073514,
    "arabic_name": "عمر محمد احمد محمد",
    "total_degree": 268
  },
  {
    "seating_no": 1073515,
    "arabic_name": "عمر محمد عبدالله قرنى فرجانى",
    "total_degree": 187.5
  },
  {
    "seating_no": 1073516,
    "arabic_name": "عمر محمد مصطفى راضى عبدالباقى",
    "total_degree": 216.5
  },
  {
    "seating_no": 1073517,
    "arabic_name": "عمر ناصر فتحى عبدالعاطى",
    "total_degree": 202.5
  },
  {
    "seating_no": 1073518,
    "arabic_name": "عمرو خالد سعد محمد",
    "total_degree": 293.5
  },
  {
    "seating_no": 1073519,
    "arabic_name": "عمرو خالد عبدالهادى محمد",
    "total_degree": 295.5
  },
  {
    "seating_no": 1073520,
    "arabic_name": "عمرو علاء رشاد احمد",
    "total_degree": 226.5
  },
  {
    "seating_no": 1073521,
    "arabic_name": "عمرو مصطفى احمد السيد",
    "total_degree": 248
  },
  {
    "seating_no": 1073522,
    "arabic_name": "فادى غطاس ملاك فارس",
    "total_degree": 265.5
  },
  {
    "seating_no": 1073523,
    "arabic_name": "فارس احمد محمد محمد",
    "total_degree": 287.5
  },
  {
    "seating_no": 1073524,
    "arabic_name": "فارس محمد كمال رمضان",
    "total_degree": 235
  },
  {
    "seating_no": 1073525,
    "arabic_name": "فارس محمود معوض عبدالحليم",
    "total_degree": 251
  },
  {
    "seating_no": 1073526,
    "arabic_name": "فهد والى محمد لطفى",
    "total_degree": 275.5
  },
  {
    "seating_no": 1073527,
    "arabic_name": "كريم احمد عبدالرحمن جمعه",
    "total_degree": 210.5
  },
  {
    "seating_no": 1073528,
    "arabic_name": "كريم اسامه عويس حامد",
    "total_degree": 283.5
  },
  {
    "seating_no": 1073529,
    "arabic_name": "كريم السيد حسنى عبدالتواب",
    "total_degree": 240
  },
  {
    "seating_no": 1073530,
    "arabic_name": "كريم السيد عبدالعظيم محمد",
    "total_degree": 232
  },
  {
    "seating_no": 1073531,
    "arabic_name": "كريم جمال عبدالعليم عبدالسلام",
    "total_degree": 263
  },
  {
    "seating_no": 1073532,
    "arabic_name": "كريم سامح عبدالعظيم السيد",
    "total_degree": 282.5
  },
  {
    "seating_no": 1073533,
    "arabic_name": "كريم سعيد شعبان علام",
    "total_degree": 212.5
  },
  {
    "seating_no": 1073534,
    "arabic_name": "كيرلس ناصر وليم جرجس",
    "total_degree": 213.5
  },
  {
    "seating_no": 1073535,
    "arabic_name": "كيرلس نبيل عدلى زكى",
    "total_degree": 209.5
  },
  {
    "seating_no": 1073536,
    "arabic_name": "مؤمن محمد قرنى عبدالجواد",
    "total_degree": 195.5
  },
  {
    "seating_no": 1073537,
    "arabic_name": "مازن احمد فتحى عبدالظاهر",
    "total_degree": 262
  },
  {
    "seating_no": 1073538,
    "arabic_name": "مازن محمد السيد احمد",
    "total_degree": 179.5
  },
  {
    "seating_no": 1073539,
    "arabic_name": "مازن محمد السيد محمد",
    "total_degree": 223
  },
  {
    "seating_no": 1073540,
    "arabic_name": "مازن محمد فرج محمد",
    "total_degree": 260
  },
  {
    "seating_no": 1073541,
    "arabic_name": "مالك محمد سعد قطب جوده",
    "total_degree": 277
  },
  {
    "seating_no": 1073542,
    "arabic_name": "محمد ابراهيم رجب عبدالحميد",
    "total_degree": 219
  },
  {
    "seating_no": 1073543,
    "arabic_name": "محمد ابوسريع السيد ابوسريع",
    "total_degree": 180
  },
  {
    "seating_no": 1073544,
    "arabic_name": "محمد احمد اسماعيل السيد",
    "total_degree": 270.5
  },
  {
    "seating_no": 1073545,
    "arabic_name": "محمد احمد رمضان ابراهيم",
    "total_degree": 209.5
  },
  {
    "seating_no": 1073546,
    "arabic_name": "محمد احمد عبدالتواب توفيق",
    "total_degree": 203
  },
  {
    "seating_no": 1073547,
    "arabic_name": "محمد احمد عبدالعزيز محمد",
    "total_degree": 214
  },
  {
    "seating_no": 1073548,
    "arabic_name": "محمد احمد عبدالمنعم السيد",
    "total_degree": 208.5
  },
  {
    "seating_no": 1073549,
    "arabic_name": "محمد احمد على محمد",
    "total_degree": 218
  },
  {
    "seating_no": 1073550,
    "arabic_name": "محمد احمد محمد عبدالحليم",
    "total_degree": 221
  },
  {
    "seating_no": 1073551,
    "arabic_name": "محمد اسماعيل فتحى محمد",
    "total_degree": 196.5
  },
  {
    "seating_no": 1073552,
    "arabic_name": "محمد اشرف جمعه امين",
    "total_degree": 233.5
  },
  {
    "seating_no": 1073553,
    "arabic_name": "محمد ايمن ابراهيم على",
    "total_degree": 198.5
  },
  {
    "seating_no": 1073554,
    "arabic_name": "محمد ايمن عبدالمنعم محمد",
    "total_degree": 216
  },
  {
    "seating_no": 1073555,
    "arabic_name": "محمد ايمن كمال قرنى",
    "total_degree": 183.5
  },
  {
    "seating_no": 1073556,
    "arabic_name": "محمد ايهاب محمد السيد",
    "total_degree": 301
  },
  {
    "seating_no": 1073557,
    "arabic_name": "محمد بدوى عبدالمنعم عثمان",
    "total_degree": 206
  },
  {
    "seating_no": 1073558,
    "arabic_name": "محمد جمال مصطفى والى ابوخزيم",
    "total_degree": 211
  },
  {
    "seating_no": 1073559,
    "arabic_name": "محمد حامد محمد فرحات",
    "total_degree": 87
  },
  {
    "seating_no": 1073560,
    "arabic_name": "محمد حسن شحاته محمد",
    "total_degree": 260
  },
  {
    "seating_no": 1073561,
    "arabic_name": "محمد حسن محمد عبدالمحسن",
    "total_degree": 282
  },
  {
    "seating_no": 1073562,
    "arabic_name": "محمد حماده السيد محمد",
    "total_degree": 227
  },
  {
    "seating_no": 1073564,
    "arabic_name": "محمد حمدى عثمان عيد",
    "total_degree": 198.5
  },
  {
    "seating_no": 1073565,
    "arabic_name": "محمد خالد جابر عبدالشافى",
    "total_degree": 271
  },
  {
    "seating_no": 1073566,
    "arabic_name": "محمد خالد عبدالجواد احمد",
    "total_degree": 240.5
  },
  {
    "seating_no": 1073567,
    "arabic_name": "محمد ربيع احمد اسماعيل",
    "total_degree": 266.5
  },
  {
    "seating_no": 1073568,
    "arabic_name": "محمد رضا رمضان على صميده",
    "total_degree": 113
  },
  {
    "seating_no": 1073569,
    "arabic_name": "محمد سراج الدين سيد عبدالجليل",
    "total_degree": 132
  },
  {
    "seating_no": 1073570,
    "arabic_name": "محمد سعيد ربيع محمد",
    "total_degree": 198.5
  },
  {
    "seating_no": 1073571,
    "arabic_name": "محمد سيد احمد عبدالرازق",
    "total_degree": 249
  },
  {
    "seating_no": 1073572,
    "arabic_name": "محمد سيد حمدى مرسى عثمان",
    "total_degree": 202
  },
  {
    "seating_no": 1073573,
    "arabic_name": "محمد سيد فتحى السيد",
    "total_degree": 270
  },
  {
    "seating_no": 1073575,
    "arabic_name": "محمد سيد محمد عبدالمعطى",
    "total_degree": 271.5
  },
  {
    "seating_no": 1073576,
    "arabic_name": "محمد سيد محمد محمد عثمان",
    "total_degree": 170.5
  },
  {
    "seating_no": 1073577,
    "arabic_name": "محمد سيد معنى عبدالرازق",
    "total_degree": 169
  },
  {
    "seating_no": 1073578,
    "arabic_name": "محمد صالح ابوبكر روبى",
    "total_degree": 162.5
  },
  {
    "seating_no": 1073579,
    "arabic_name": "محمد طارق امين عوض",
    "total_degree": 182.5
  },
  {
    "seating_no": 1073580,
    "arabic_name": "محمد طارق محمد جبالى",
    "total_degree": 267.5
  },
  {
    "seating_no": 1073581,
    "arabic_name": "محمد عادل السيد عبدالسلام",
    "total_degree": 173
  },
  {
    "seating_no": 1073582,
    "arabic_name": "محمد عادل سيد جوده عبدالله",
    "total_degree": 239.5
  },
  {
    "seating_no": 1073583,
    "arabic_name": "محمد عادل عبدالفضيل محمد",
    "total_degree": 269.5
  },
  {
    "seating_no": 1073584,
    "arabic_name": "محمد عاصم رمضان عبدالسلام",
    "total_degree": 279
  },
  {
    "seating_no": 1073585,
    "arabic_name": "محمد عبدالتواب ابوبكر عبدالتواب",
    "total_degree": 151
  },
  {
    "seating_no": 1073586,
    "arabic_name": "محمد عبدالتواب احمد احمد",
    "total_degree": 196.5
  },
  {
    "seating_no": 1073587,
    "arabic_name": "محمد عبدالتواب عبدالتواب بركات",
    "total_degree": 287
  },
  {
    "seating_no": 1073588,
    "arabic_name": "محمد عبدالرحمن محمد محفوظ",
    "total_degree": 223
  },
  {
    "seating_no": 1073589,
    "arabic_name": "محمد عبدالعظيم محمد عبدالعظيم",
    "total_degree": 192
  },
  {
    "seating_no": 1073590,
    "arabic_name": "محمد عبدالله شعبان محمد عبدالسلام",
    "total_degree": 0
  },
  {
    "seating_no": 1073591,
    "arabic_name": "محمد عصام احمد حلمى",
    "total_degree": 212
  },
  {
    "seating_no": 1073592,
    "arabic_name": "محمد عطاء مصطفى زكى محمد هلال",
    "total_degree": 185.5
  },
  {
    "seating_no": 1073593,
    "arabic_name": "محمد على عبدالعال سعيد",
    "total_degree": 229.5
  },
  {
    "seating_no": 1073594,
    "arabic_name": "محمد عوض حسين رضوان",
    "total_degree": 278.5
  },
  {
    "seating_no": 1073595,
    "arabic_name": "محمد فارس احمد عبدالفتاح",
    "total_degree": 306
  },
  {
    "seating_no": 1073596,
    "arabic_name": "محمد قرنى محمد احمد معوض",
    "total_degree": 223.5
  },
  {
    "seating_no": 1073597,
    "arabic_name": "محمد قرنى محمد عبدالهادى",
    "total_degree": 148
  },
  {
    "seating_no": 1073598,
    "arabic_name": "محمد محمد زهير ابراهيم محفوظ",
    "total_degree": 110
  },
  {
    "seating_no": 1073599,
    "arabic_name": "محمد محمود حسين شعبان",
    "total_degree": 267.5
  },
  {
    "seating_no": 1073600,
    "arabic_name": "محمد محمود شحاته محمود",
    "total_degree": 241.5
  },
  {
    "seating_no": 1073601,
    "arabic_name": "محمد محمود متولى متولى",
    "total_degree": 296.5
  },
  {
    "seating_no": 1073602,
    "arabic_name": "محمد ممدوح عبدالعال قطب",
    "total_degree": 253
  },
  {
    "seating_no": 1073603,
    "arabic_name": "محمد مهدى توفيق عبدالله",
    "total_degree": 208
  },
  {
    "seating_no": 1073604,
    "arabic_name": "محمد هانى محمد جوده",
    "total_degree": 214.5
  },
  {
    "seating_no": 1073605,
    "arabic_name": "محمود ابراهيم عبدالله ابراهيم محمد",
    "total_degree": 246
  },
  {
    "seating_no": 1073606,
    "arabic_name": "محمود احمد ابوزيد محمد",
    "total_degree": 198
  },
  {
    "seating_no": 1073607,
    "arabic_name": "محمود احمد محمود على",
    "total_degree": 210.5
  },
  {
    "seating_no": 1073608,
    "arabic_name": "محمود جمال محمود قاسم",
    "total_degree": 201.5
  },
  {
    "seating_no": 1073609,
    "arabic_name": "محمود ربيع عبدالعظيم محمد",
    "total_degree": 191.5
  },
  {
    "seating_no": 1073610,
    "arabic_name": "محمود رجب فتحى عبدالمقصود",
    "total_degree": 247.5
  },
  {
    "seating_no": 1073611,
    "arabic_name": "محمود سعد محمد عبدالمقصود",
    "total_degree": 232.5
  },
  {
    "seating_no": 1073612,
    "arabic_name": "محمود سيد احمد محمد",
    "total_degree": 207.5
  },
  {
    "seating_no": 1073613,
    "arabic_name": "محمود عبدالتواب محمود محمد",
    "total_degree": 175
  },
  {
    "seating_no": 1073614,
    "arabic_name": "محمود عماد عبدالحليم منصور",
    "total_degree": 182.5
  },
  {
    "seating_no": 1073615,
    "arabic_name": "محمود عيد قرنى محمود عبدالباقى",
    "total_degree": 207
  },
  {
    "seating_no": 1073616,
    "arabic_name": "محمود فرج محمد رمضان",
    "total_degree": 213
  },
  {
    "seating_no": 1073617,
    "arabic_name": "محمود محمد عبدالرحمن عبدالحفيظ",
    "total_degree": 229.5
  },
  {
    "seating_no": 1073618,
    "arabic_name": "محمود محمد محمود السيد",
    "total_degree": 273
  },
  {
    "seating_no": 1073619,
    "arabic_name": "محمود نجم محمد محمد",
    "total_degree": 270.5
  },
  {
    "seating_no": 1073620,
    "arabic_name": "مروان احمد حسنى عبدالتواب",
    "total_degree": 296
  },
  {
    "seating_no": 1073621,
    "arabic_name": "مروان احمد ربيع احمد",
    "total_degree": 171
  },
  {
    "seating_no": 1073622,
    "arabic_name": "مروان حسين خليل احمد",
    "total_degree": 213
  },
  {
    "seating_no": 1073623,
    "arabic_name": "مروان سيد يونس محمود",
    "total_degree": 246.5
  },
  {
    "seating_no": 1073624,
    "arabic_name": "مروان محمد حمدى جمعه",
    "total_degree": 255.5
  },
  {
    "seating_no": 1073625,
    "arabic_name": "مروان ممدوح ضرار بيومى",
    "total_degree": 283
  },
  {
    "seating_no": 1073626,
    "arabic_name": "مروان وليد السيد على خالد",
    "total_degree": 247.5
  },
  {
    "seating_no": 1073627,
    "arabic_name": "مصطفى احمد محمد عبدالتواب",
    "total_degree": 258
  },
  {
    "seating_no": 1073628,
    "arabic_name": "مصطفى جمعه حنفى محمود",
    "total_degree": 245.5
  },
  {
    "seating_no": 1073629,
    "arabic_name": "مصطفى جمعه شعبان محمود",
    "total_degree": 302.5
  },
  {
    "seating_no": 1073630,
    "arabic_name": "مصطفى على محمد احمد",
    "total_degree": 274.5
  },
  {
    "seating_no": 1073631,
    "arabic_name": "مصطفى محمد رجب محمد",
    "total_degree": 177.5
  },
  {
    "seating_no": 1073632,
    "arabic_name": "مصطفى محمد سعداوى صابر",
    "total_degree": 207
  },
  {
    "seating_no": 1073633,
    "arabic_name": "مصطفى محمد مصطفى احمد",
    "total_degree": 260.5
  },
  {
    "seating_no": 1073634,
    "arabic_name": "مصطفى محمود محمد عبدالفتاح",
    "total_degree": 259
  },
  {
    "seating_no": 1073635,
    "arabic_name": "مصطفى محمود معوض عبدالباقى",
    "total_degree": 243.5
  },
  {
    "seating_no": 1073636,
    "arabic_name": "معاذ السيد عبدالعظيم على",
    "total_degree": 202.5
  },
  {
    "seating_no": 1073637,
    "arabic_name": "معاذ هانى محمد توفيق",
    "total_degree": 162.5
  },
  {
    "seating_no": 1073638,
    "arabic_name": "معتز احمد عبدالستار عيد",
    "total_degree": 207.5
  },
  {
    "seating_no": 1073639,
    "arabic_name": "معتز اشرف شحاته عبدالوهاب احمد",
    "total_degree": 175.5
  },
  {
    "seating_no": 1073640,
    "arabic_name": "معتز حسين رجب طلبه",
    "total_degree": 271.5
  },
  {
    "seating_no": 1073641,
    "arabic_name": "معتز محمد حسين محمد",
    "total_degree": 272.5
  },
  {
    "seating_no": 1073642,
    "arabic_name": "معتز هشام حسين حسان",
    "total_degree": 229
  },
  {
    "seating_no": 1073643,
    "arabic_name": "مهاب ايهاب كمال متولى",
    "total_degree": 267.5
  },
  {
    "seating_no": 1073644,
    "arabic_name": "مهند احمد عبدالمقصود سعداوى",
    "total_degree": 212
  },
  {
    "seating_no": 1073645,
    "arabic_name": "مهند صلاح فوزى عبدالحميد",
    "total_degree": 243
  },
  {
    "seating_no": 1073646,
    "arabic_name": "مهند وائل عويس عبداللطيف",
    "total_degree": 204
  },
  {
    "seating_no": 1073647,
    "arabic_name": "نادر عادل عويس عبدالتواب",
    "total_degree": 170.5
  },
  {
    "seating_no": 1073648,
    "arabic_name": "نور محمد ربيع مصطفى",
    "total_degree": 90.5
  },
  {
    "seating_no": 1073649,
    "arabic_name": "نورالدين اشرف محمود محمد",
    "total_degree": 232.5
  },
  {
    "seating_no": 1073650,
    "arabic_name": "نورالدين محمود عبدالفتاح احمد محمد",
    "total_degree": 232.5
  },
  {
    "seating_no": 1073651,
    "arabic_name": "هانى عيد عبدالحليم جنيدى",
    "total_degree": 279
  },
  {
    "seating_no": 1073652,
    "arabic_name": "هشام اشرف عبدالحكم قطب",
    "total_degree": 242.5
  },
  {
    "seating_no": 1073653,
    "arabic_name": "ياسين السيد رجب عبدالعال",
    "total_degree": 195.5
  },
  {
    "seating_no": 1073654,
    "arabic_name": "ياسين عماد خميس سالم",
    "total_degree": 260.5
  },
  {
    "seating_no": 1073655,
    "arabic_name": "يحيى محمد عبدالتواب عبدالوهاب",
    "total_degree": 228.5
  },
  {
    "seating_no": 1073656,
    "arabic_name": "يوسف احمد احمد محمد اسماعيل",
    "total_degree": 164
  },
  {
    "seating_no": 1073657,
    "arabic_name": "يوسف احمد السيد عويس",
    "total_degree": 187
  },
  {
    "seating_no": 1073658,
    "arabic_name": "يوسف احمد السيد محمد",
    "total_degree": 177
  },
  {
    "seating_no": 1073659,
    "arabic_name": "يوسف بدوى محمد غانم",
    "total_degree": 228
  },
  {
    "seating_no": 1073660,
    "arabic_name": "يوسف جمال رمضان عبدالوهاب",
    "total_degree": 281.5
  },
  {
    "seating_no": 1073661,
    "arabic_name": "يوسف حسن محمد حسن",
    "total_degree": 271
  },
  {
    "seating_no": 1073662,
    "arabic_name": "يوسف حسنى قرنى عبدالحميد",
    "total_degree": 238
  },
  {
    "seating_no": 1073663,
    "arabic_name": "يوسف حماده عبداللطيف محمد",
    "total_degree": 278
  },
  {
    "seating_no": 1073664,
    "arabic_name": "يوسف سليمان محمد عبدالعزيز",
    "total_degree": 0
  },
  {
    "seating_no": 1073665,
    "arabic_name": "يوسف شعبان فتحى عبدالعاطى",
    "total_degree": 277.5
  },
  {
    "seating_no": 1073666,
    "arabic_name": "يوسف شعبان محمد رجب",
    "total_degree": 296.5
  },
  {
    "seating_no": 1073667,
    "arabic_name": "يوسف صلاح محمد قرنى",
    "total_degree": 280.5
  },
  {
    "seating_no": 1073668,
    "arabic_name": "يوسف طه عبدالعليم محمد",
    "total_degree": 228
  },
  {
    "seating_no": 1073669,
    "arabic_name": "يوسف عادل عبدالرحمن محمد",
    "total_degree": 188.5
  },
  {
    "seating_no": 1073670,
    "arabic_name": "يوسف عصام عشرى محمود",
    "total_degree": 260.5
  },
  {
    "seating_no": 1073671,
    "arabic_name": "يوسف كارم فتحى محمود",
    "total_degree": 261.5
  },
  {
    "seating_no": 1073672,
    "arabic_name": "يوسف كامل سيد رمضان",
    "total_degree": 237
  },
  {
    "seating_no": 1073673,
    "arabic_name": "يوسف محمد احمد معبد",
    "total_degree": 241
  },
  {
    "seating_no": 1073674,
    "arabic_name": "يوسف محمد السيد السيد",
    "total_degree": 262
  },
  {
    "seating_no": 1073675,
    "arabic_name": "يوسف محمد رمضان عبدالله",
    "total_degree": 217.5
  },
  {
    "seating_no": 1073676,
    "arabic_name": "يوسف محمد رمضان على احمد",
    "total_degree": 173.5
  },
  {
    "seating_no": 1073677,
    "arabic_name": "يوسف محمد عبدالله طلب",
    "total_degree": 290.5
  },
  {
    "seating_no": 1073678,
    "arabic_name": "يوسف محمد فوزى احمد",
    "total_degree": 269.5
  },
  {
    "seating_no": 1073679,
    "arabic_name": "يوسف مصطفى عبدالله عبدالمقصود",
    "total_degree": 271.5
  },
  {
    "seating_no": 1073680,
    "arabic_name": "احمد عبدالله مسعود عبدالله",
    "total_degree": 189.5
  },
  {
    "seating_no": 1073681,
    "arabic_name": "احمد ماهر ربيع احمد",
    "total_degree": 250
  },
  {
    "seating_no": 1073682,
    "arabic_name": "احمد محفوظ عبدالحليم محفوظ",
    "total_degree": 305.5
  },
  {
    "seating_no": 1073683,
    "arabic_name": "احمد محمد قرنى السيد",
    "total_degree": 262.5
  },
  {
    "seating_no": 1073684,
    "arabic_name": "احمد محمد مرزوق محمود",
    "total_degree": 248.5
  },
  {
    "seating_no": 1073685,
    "arabic_name": "احمد محمود عوض محمد",
    "total_degree": 228.5
  },
  {
    "seating_no": 1073686,
    "arabic_name": "احمد مهدى سليمان السيد",
    "total_degree": 284
  },
  {
    "seating_no": 1073687,
    "arabic_name": "استيفن سمير سمير كامل",
    "total_degree": 200
  },
  {
    "seating_no": 1073688,
    "arabic_name": "البشير فتحى على محمود",
    "total_degree": 299
  },
  {
    "seating_no": 1073689,
    "arabic_name": "امير ماجد كامل جادالسيد",
    "total_degree": 227
  },
  {
    "seating_no": 1073691,
    "arabic_name": "بيتر جمال فؤاد عزب",
    "total_degree": 257
  },
  {
    "seating_no": 1073692,
    "arabic_name": "جوناثان جورج يوسف شكرى",
    "total_degree": 293
  },
  {
    "seating_no": 1073693,
    "arabic_name": "حسين محمد حسين محمد",
    "total_degree": 220.5
  },
  {
    "seating_no": 1073694,
    "arabic_name": "رومانى نبيل فرج الله ابراهيم",
    "total_degree": 243.5
  },
  {
    "seating_no": 1073695,
    "arabic_name": "زياد محمد قرنى فرج",
    "total_degree": 248
  },
  {
    "seating_no": 1073696,
    "arabic_name": "سيف الدين ممدوح محمد عبدالعزيز احمد",
    "total_degree": 211.5
  },
  {
    "seating_no": 1073697,
    "arabic_name": "عبدالرحمن خالد سيد سليمان",
    "total_degree": 238
  },
  {
    "seating_no": 1073698,
    "arabic_name": "عبدالرحمن عادل محمد عبدالعزيز محمد",
    "total_degree": 204
  },
  {
    "seating_no": 1073699,
    "arabic_name": "عبدالرحمن محمود احمد محمد",
    "total_degree": 194
  },
  {
    "seating_no": 1073700,
    "arabic_name": "عبدالله احمد حسين عباس",
    "total_degree": 214
  },
  {
    "seating_no": 1073701,
    "arabic_name": "على محمد على عبدالباقى",
    "total_degree": 227
  },
  {
    "seating_no": 1073702,
    "arabic_name": "محمد حسن محمد حسين معوض",
    "total_degree": 287.5
  },
  {
    "seating_no": 1073703,
    "arabic_name": "محمد خالد محمد عبدالفتاح",
    "total_degree": 289.5
  },
  {
    "seating_no": 1073704,
    "arabic_name": "محمد عبدالناصر محمد رمضان",
    "total_degree": 228
  },
  {
    "seating_no": 1073705,
    "arabic_name": "محمد عمر عبدالعليم عبدالواحد",
    "total_degree": 268.5
  },
  {
    "seating_no": 1073706,
    "arabic_name": "محمود محمد عبدالعظيم حسين",
    "total_degree": 251.5
  },
  {
    "seating_no": 1073707,
    "arabic_name": "محمود محمد فتحى احمد",
    "total_degree": 236
  },
  {
    "seating_no": 1073708,
    "arabic_name": "مروان عمر محمد ربيع",
    "total_degree": 197
  },
  {
    "seating_no": 1073709,
    "arabic_name": "مينا خليل رمضان خليل اسحق",
    "total_degree": 199.5
  },
  {
    "seating_no": 1073710,
    "arabic_name": "الاء السيد حمدي محمد على",
    "total_degree": 182
  },
  {
    "seating_no": 1073711,
    "arabic_name": "امانى احمد عبدالمجيد عبدالسميع",
    "total_degree": 287.5
  },
  {
    "seating_no": 1073712,
    "arabic_name": "امل محمود مظهر معوض",
    "total_degree": 271
  },
  {
    "seating_no": 1073713,
    "arabic_name": "امنيه شعبان عويس عبدالله",
    "total_degree": 148
  },
  {
    "seating_no": 1073714,
    "arabic_name": "ايمان نصر شعبان حسين",
    "total_degree": 180
  },
  {
    "seating_no": 1073715,
    "arabic_name": "بسمله حسين سليمان عبدالحميد",
    "total_degree": 225.5
  },
  {
    "seating_no": 1073716,
    "arabic_name": "بسمله سامح السيد عبدالفتاح",
    "total_degree": 258.5
  },
  {
    "seating_no": 1073717,
    "arabic_name": "بسمله محمود خميس كامل",
    "total_degree": 248
  },
  {
    "seating_no": 1073718,
    "arabic_name": "جنا محمود جلال عبدالمقصود",
    "total_degree": 128
  },
  {
    "seating_no": 1073719,
    "arabic_name": "جولينا عصام ثابت لطيف",
    "total_degree": 202.5
  },
  {
    "seating_no": 1073720,
    "arabic_name": "حبيبه عمرو مصطفي جبريل",
    "total_degree": 236.5
  },
  {
    "seating_no": 1073721,
    "arabic_name": "خلود خالد حلمى محمد طنطاوى",
    "total_degree": 101
  },
  {
    "seating_no": 1073722,
    "arabic_name": "خلود خالد عبدالتواب عبدالغنى",
    "total_degree": 141.5
  },
  {
    "seating_no": 1073723,
    "arabic_name": "دعاء عبدالله محمد حمد",
    "total_degree": 208.5
  },
  {
    "seating_no": 1073724,
    "arabic_name": "دعاء عصام شعبان عثمان",
    "total_degree": 226
  },
  {
    "seating_no": 1073725,
    "arabic_name": "روان عماد طلبه على",
    "total_degree": 258
  },
  {
    "seating_no": 1073726,
    "arabic_name": "رويدا عماد سيد قرنى",
    "total_degree": 117
  },
  {
    "seating_no": 1073727,
    "arabic_name": "ريهام محمد حسن عبدالرحيم",
    "total_degree": 226.5
  },
  {
    "seating_no": 1073728,
    "arabic_name": "ساره سعيد ابراهيم احمد",
    "total_degree": 165
  },
  {
    "seating_no": 1073729,
    "arabic_name": "ساره عبدالعليم عبدالمجيد عبدالسميع",
    "total_degree": 180
  },
  {
    "seating_no": 1073730,
    "arabic_name": "شذى عمر محمد عبدالعزيز",
    "total_degree": 194
  },
  {
    "seating_no": 1073731,
    "arabic_name": "شروق محمود محمد عبدالسلام",
    "total_degree": 240
  },
  {
    "seating_no": 1073732,
    "arabic_name": "شهد احمد على محمود",
    "total_degree": 216
  },
  {
    "seating_no": 1073733,
    "arabic_name": "شيماء حماده سيد روبى",
    "total_degree": 199
  },
  {
    "seating_no": 1073734,
    "arabic_name": "فاطمه جمال عبدالله قرنى",
    "total_degree": 254.5
  },
  {
    "seating_no": 1073735,
    "arabic_name": "مارينا معوض نجدى شهيد",
    "total_degree": 242.5
  },
  {
    "seating_no": 1073736,
    "arabic_name": "مريم احمد بليدى محمد سعداوي",
    "total_degree": 228
  },
  {
    "seating_no": 1073737,
    "arabic_name": "مريم سامي اسماعيل عيد",
    "total_degree": 189
  },
  {
    "seating_no": 1073738,
    "arabic_name": "مريم عزت عطا نصر",
    "total_degree": 151
  },
  {
    "seating_no": 1073739,
    "arabic_name": "مريم عماد نجيب عياد",
    "total_degree": 214.5
  },
  {
    "seating_no": 1073740,
    "arabic_name": "مريم محمود محمد امين",
    "total_degree": 282
  },
  {
    "seating_no": 1073741,
    "arabic_name": "ملك احمد سليمان عبدالحميد",
    "total_degree": 255.5
  },
  {
    "seating_no": 1073742,
    "arabic_name": "ملك احمد عبدالعزيز محمد",
    "total_degree": 208
  },
  {
    "seating_no": 1073743,
    "arabic_name": "منه الله جمال سلطان حسن",
    "total_degree": 169.5
  },
  {
    "seating_no": 1073744,
    "arabic_name": "منه طه محمود احمد طلبه",
    "total_degree": 223
  },
  {
    "seating_no": 1073745,
    "arabic_name": "موده عصام محمد عبدالنبى",
    "total_degree": 244.5
  },
  {
    "seating_no": 1073746,
    "arabic_name": "ناهد سمير سيد عبدالصمد",
    "total_degree": 215.5
  },
  {
    "seating_no": 1073747,
    "arabic_name": "نورهان شعبان مفتاح امين",
    "total_degree": 160
  },
  {
    "seating_no": 1073748,
    "arabic_name": "نورهان صالح ربيع سيد",
    "total_degree": 239.5
  },
  {
    "seating_no": 1073749,
    "arabic_name": "نورهان طارق طه حموده",
    "total_degree": 258.5
  },
  {
    "seating_no": 1073750,
    "arabic_name": "نورهان مصطفى على عبدالبصير",
    "total_degree": 159
  },
  {
    "seating_no": 1073751,
    "arabic_name": "هاجر عويس محمود محمد",
    "total_degree": 258
  },
  {
    "seating_no": 1073752,
    "arabic_name": "هبه خالد عبدالستار يوسف",
    "total_degree": 229
  },
  {
    "seating_no": 1073753,
    "arabic_name": "هدى منجى سيد حلمى",
    "total_degree": 219.5
  },
  {
    "seating_no": 1073754,
    "arabic_name": "هنا محمود على عبدالحميد",
    "total_degree": 228
  },
  {
    "seating_no": 1073755,
    "arabic_name": "ياسمين سمير على محمد",
    "total_degree": 223
  },
  {
    "seating_no": 1073756,
    "arabic_name": "ياسمين عبدالله عبدالقوى عبدالله",
    "total_degree": 285
  },
  {
    "seating_no": 1073757,
    "arabic_name": "يمنى احمد محمود عبداللطيف",
    "total_degree": 206
  },
  {
    "seating_no": 1073758,
    "arabic_name": "ابرار سالم محمد شاكر",
    "total_degree": 237
  },
  {
    "seating_no": 1073759,
    "arabic_name": "اروى احمد محمد عبدالفتاح",
    "total_degree": 257.5
  },
  {
    "seating_no": 1073760,
    "arabic_name": "اروى شعبان محمود عبدالفتاح",
    "total_degree": 200.5
  },
  {
    "seating_no": 1073761,
    "arabic_name": "اسراء جابر عبدالعليم عبدالسميع",
    "total_degree": 142.5
  },
  {
    "seating_no": 1073762,
    "arabic_name": "اسراء رمضان عبدالرحمن عبدالحفيظ",
    "total_degree": 235.5
  },
  {
    "seating_no": 1073763,
    "arabic_name": "اسراء سعد محمود سيد",
    "total_degree": 173.5
  },
  {
    "seating_no": 1073764,
    "arabic_name": "اسراء عبيد خلف عبدالعاطى",
    "total_degree": 146.5
  },
  {
    "seating_no": 1073765,
    "arabic_name": "اسراء علي ابراهيم علي ابراهيم",
    "total_degree": 147
  },
  {
    "seating_no": 1073766,
    "arabic_name": "اسراء فرج على محمد",
    "total_degree": 211.5
  },
  {
    "seating_no": 1073767,
    "arabic_name": "اسراء محمد عبداللطيف عبدالرازق",
    "total_degree": 157.5
  },
  {
    "seating_no": 1073768,
    "arabic_name": "اسراء محمود خليفه عبدالمنطلب",
    "total_degree": 262
  },
  {
    "seating_no": 1073769,
    "arabic_name": "اسراء ياسر فاروق غانم",
    "total_degree": 162.5
  },
  {
    "seating_no": 1073770,
    "arabic_name": "اسماء احمد عبدالتواب قرنى",
    "total_degree": 129.5
  },
  {
    "seating_no": 1073771,
    "arabic_name": "اسماء امير عبدالجواد عبدالجواد",
    "total_degree": 181.5
  },
  {
    "seating_no": 1073772,
    "arabic_name": "اسماء ايوب جمعه فرج",
    "total_degree": 163.5
  },
  {
    "seating_no": 1073773,
    "arabic_name": "اسماء حماده احمد محمد",
    "total_degree": 210
  },
  {
    "seating_no": 1073774,
    "arabic_name": "اسماء حماده حسن مهدي",
    "total_degree": 244.5
  },
  {
    "seating_no": 1073775,
    "arabic_name": "اسماء خالد جابر صميده",
    "total_degree": 248
  },
  {
    "seating_no": 1073776,
    "arabic_name": "اسماء رجب قرنى رمضان",
    "total_degree": 161.5
  },
  {
    "seating_no": 1073777,
    "arabic_name": "اسماء رجب محمود محمد",
    "total_degree": 229
  },
  {
    "seating_no": 1073778,
    "arabic_name": "اسماء سيد عبدالكريم محمد",
    "total_degree": 150
  },
  {
    "seating_no": 1073779,
    "arabic_name": "اسماء سيد محمد عبدالفتاح",
    "total_degree": 306
  },
  {
    "seating_no": 1073780,
    "arabic_name": "اسماء عبدالظاهر محمد عبدالظاهر",
    "total_degree": 253.5
  },
  {
    "seating_no": 1073781,
    "arabic_name": "اسماء عبدالله سيد احمد علي",
    "total_degree": 187.5
  },
  {
    "seating_no": 1073782,
    "arabic_name": "اسماء عصام محمد شعبان",
    "total_degree": 155
  },
  {
    "seating_no": 1073783,
    "arabic_name": "اسماء محمد فتحى محمد اسماعيل",
    "total_degree": 224.5
  },
  {
    "seating_no": 1073784,
    "arabic_name": "اسماء محمد محمد رمضان جمعه",
    "total_degree": 290.5
  },
  {
    "seating_no": 1073785,
    "arabic_name": "اشواق عطيه على طرفايه",
    "total_degree": 224.5
  },
  {
    "seating_no": 1073786,
    "arabic_name": "اشواق عيد محمود عبدالله",
    "total_degree": 189.5
  },
  {
    "seating_no": 1073787,
    "arabic_name": "افنان احمد السيد محمد",
    "total_degree": 286
  },
  {
    "seating_no": 1073788,
    "arabic_name": "افنان شعبان عبدالتواب ساعدي",
    "total_degree": 288
  },
  {
    "seating_no": 1073789,
    "arabic_name": "الاء طلعت ابراهيم عبدالرازق",
    "total_degree": 136
  },
  {
    "seating_no": 1073790,
    "arabic_name": "الاء طه محمد خليفه",
    "total_degree": 228.5
  },
  {
    "seating_no": 1073791,
    "arabic_name": "الاء عبدالحليم محمد عبدالحليم",
    "total_degree": 177.5
  },
  {
    "seating_no": 1073792,
    "arabic_name": "الاء عبدالهادى رجب عبدالهادى",
    "total_degree": 210.5
  },
  {
    "seating_no": 1073793,
    "arabic_name": "امال محمد عطيه السيد",
    "total_degree": 219.5
  },
  {
    "seating_no": 1073794,
    "arabic_name": "امانى ربيع احمد السيد",
    "total_degree": 161.5
  },
  {
    "seating_no": 1073795,
    "arabic_name": "امانى علاءالدين عوض قرنى",
    "total_degree": 142
  },
  {
    "seating_no": 1073796,
    "arabic_name": "امانى مصطفى احمد محمد",
    "total_degree": 198.5
  },
  {
    "seating_no": 1073797,
    "arabic_name": "امل خميس سعيد ابراهيم",
    "total_degree": 164
  },
  {
    "seating_no": 1073798,
    "arabic_name": "امل شعبان محمد محمود",
    "total_degree": 183
  },
  {
    "seating_no": 1073799,
    "arabic_name": "امنيه خالد عبدالحليم حلمى",
    "total_degree": 229
  },
  {
    "seating_no": 1073800,
    "arabic_name": "امنيه سلطان سيد شيلابى",
    "total_degree": 169.5
  },
  {
    "seating_no": 1073801,
    "arabic_name": "امنيه على رمضان حسانين",
    "total_degree": 204.5
  },
  {
    "seating_no": 1073802,
    "arabic_name": "امنيه محمد جميل عبدالحميد",
    "total_degree": 191.5
  },
  {
    "seating_no": 1073803,
    "arabic_name": "امنيه هانى ابوشناف محمد",
    "total_degree": 211.5
  },
  {
    "seating_no": 1073804,
    "arabic_name": "اميره اشرف السيد ابراهيم حسين",
    "total_degree": 229.5
  },
  {
    "seating_no": 1073805,
    "arabic_name": "اميره حسن على عبدالعزيز",
    "total_degree": 205
  },
  {
    "seating_no": 1073806,
    "arabic_name": "اميره حسين احمد محمد",
    "total_degree": 188.5
  },
  {
    "seating_no": 1073807,
    "arabic_name": "اميره خالد عويس شافعى",
    "total_degree": 199.5
  },
  {
    "seating_no": 1073808,
    "arabic_name": "اميره سلامه محمد رمضان",
    "total_degree": 155
  },
  {
    "seating_no": 1073809,
    "arabic_name": "اميره على يحى احمد",
    "total_degree": 223
  },
  {
    "seating_no": 1073810,
    "arabic_name": "اميره محسن عبدالمنعم فهمي",
    "total_degree": 132.5
  },
  {
    "seating_no": 1073811,
    "arabic_name": "اميمه سيد شعبان محمد عبدالله",
    "total_degree": 164
  },
  {
    "seating_no": 1073812,
    "arabic_name": "امينه محمد جمال محمد",
    "total_degree": 138.5
  },
  {
    "seating_no": 1073813,
    "arabic_name": "انجى عصام كامل عزيز",
    "total_degree": 158.5
  },
  {
    "seating_no": 1073814,
    "arabic_name": "ايات فارس راضي زكي",
    "total_degree": 257.5
  },
  {
    "seating_no": 1073815,
    "arabic_name": "ايرينى تامر صلاح منصور",
    "total_degree": 199
  },
  {
    "seating_no": 1073816,
    "arabic_name": "ايمان جوده سيد جوده",
    "total_degree": 231.5
  },
  {
    "seating_no": 1073817,
    "arabic_name": "ايمان شعبان صالح محمد",
    "total_degree": 222
  },
  {
    "seating_no": 1073818,
    "arabic_name": "ايناس محمود احمد عبدالتواب",
    "total_degree": 271.5
  },
  {
    "seating_no": 1073819,
    "arabic_name": "ايه احمد محمد راضى معوض",
    "total_degree": 154
  },
  {
    "seating_no": 1073820,
    "arabic_name": "ايه السيد ابراهيم محمد",
    "total_degree": 278
  },
  {
    "seating_no": 1073821,
    "arabic_name": "ايه بليدى علوانى سلامه",
    "total_degree": 173.5
  },
  {
    "seating_no": 1073822,
    "arabic_name": "ايه جمال رمضان محمد",
    "total_degree": 240.5
  },
  {
    "seating_no": 1073823,
    "arabic_name": "ايه خالد عويس عبدالعاطى",
    "total_degree": 230.5
  },
  {
    "seating_no": 1073824,
    "arabic_name": "ايه خالد محمد فرج",
    "total_degree": 202
  },
  {
    "seating_no": 1073825,
    "arabic_name": "ايه رجب على محمد",
    "total_degree": 236
  },
  {
    "seating_no": 1073826,
    "arabic_name": "ايه زكى ربيع زكى",
    "total_degree": 250.5
  },
  {
    "seating_no": 1073827,
    "arabic_name": "ايه سيد قاسم عبدالحميد",
    "total_degree": 183
  },
  {
    "seating_no": 1073828,
    "arabic_name": "ايه شعبان على محمد",
    "total_degree": 199.5
  },
  {
    "seating_no": 1073829,
    "arabic_name": "ايه عبدالرازق عبدالحميد محمد",
    "total_degree": 153.5
  },
  {
    "seating_no": 1073830,
    "arabic_name": "ايه عصام عبدالمنعم سيد",
    "total_degree": 193.5
  },
  {
    "seating_no": 1073831,
    "arabic_name": "ايه عيد الصافى سليمان",
    "total_degree": 133
  },
  {
    "seating_no": 1073832,
    "arabic_name": "ايه محمد عبدالتواب مصطفى",
    "total_degree": 183
  },
  {
    "seating_no": 1073833,
    "arabic_name": "ايه محمد على احمد",
    "total_degree": 213.5
  },
  {
    "seating_no": 1073834,
    "arabic_name": "ايه محمد قطب يحى",
    "total_degree": 53
  },
  {
    "seating_no": 1073835,
    "arabic_name": "ايه محمود محمد عبدالعزيز",
    "total_degree": 167
  },
  {
    "seating_no": 1073836,
    "arabic_name": "ايه منصور عبدالكريم عبدالغنى",
    "total_degree": 0
  },
  {
    "seating_no": 1073837,
    "arabic_name": "بسمله احمد السيد عبدالظاهر",
    "total_degree": 177
  },
  {
    "seating_no": 1073838,
    "arabic_name": "بسمله احمد محمد احمد",
    "total_degree": 293.5
  },
  {
    "seating_no": 1073839,
    "arabic_name": "بسمله خالد عبدالعزيز عبدالجواد",
    "total_degree": 273.5
  },
  {
    "seating_no": 1073840,
    "arabic_name": "بسمله شعبان السيد محمد",
    "total_degree": 289
  },
  {
    "seating_no": 1073841,
    "arabic_name": "بسمله عادل فكرى عباس احمد",
    "total_degree": 219
  },
  {
    "seating_no": 1073842,
    "arabic_name": "بسمله عمر عبدالله مطلوب",
    "total_degree": 136.5
  },
  {
    "seating_no": 1073843,
    "arabic_name": "بسمله محمد جمعه رجب",
    "total_degree": 181.5
  },
  {
    "seating_no": 1073844,
    "arabic_name": "بسمه رزق رجب عبدالحميد",
    "total_degree": 254
  },
  {
    "seating_no": 1073845,
    "arabic_name": "بسمه شعبان منصور جوده",
    "total_degree": 149
  },
  {
    "seating_no": 1073846,
    "arabic_name": "بسنت جمعه عويس عبدالتواب",
    "total_degree": 262
  },
  {
    "seating_no": 1073847,
    "arabic_name": "بسنت سعد سيد عبدالعال",
    "total_degree": 180
  },
  {
    "seating_no": 1073848,
    "arabic_name": "بسنت شعبان صلاح شعبان",
    "total_degree": 121.5
  },
  {
    "seating_no": 1073849,
    "arabic_name": "بسنت طه محمد رجب",
    "total_degree": 231.5
  },
  {
    "seating_no": 1073850,
    "arabic_name": "بسنت عماد غبريال لطيف",
    "total_degree": 174.5
  },
  {
    "seating_no": 1073851,
    "arabic_name": "بسنت عمرو محمد محمد",
    "total_degree": 236
  },
  {
    "seating_no": 1073852,
    "arabic_name": "بسينه محمد فرغل عبدالهادى",
    "total_degree": 200
  },
  {
    "seating_no": 1073853,
    "arabic_name": "تسابيح محمد حامد محمد",
    "total_degree": 223.5
  },
  {
    "seating_no": 1073854,
    "arabic_name": "تسنيم احمد محمود عبدالقادر",
    "total_degree": 302.5
  },
  {
    "seating_no": 1073855,
    "arabic_name": "تسنيم محمد انور عبدالباقى",
    "total_degree": 248
  },
  {
    "seating_no": 1073856,
    "arabic_name": "تسنيم وائل لطفى رفاعى",
    "total_degree": 217
  },
  {
    "seating_no": 1073857,
    "arabic_name": "جنا احمد عبدالله عبدالقادر",
    "total_degree": 298
  },
  {
    "seating_no": 1073858,
    "arabic_name": "جنا اشرف محمد حسين",
    "total_degree": 256.5
  },
  {
    "seating_no": 1073859,
    "arabic_name": "جنا السيد رجب جمعه",
    "total_degree": 266
  },
  {
    "seating_no": 1073860,
    "arabic_name": "جنا وليد السيد رفاعى",
    "total_degree": 204.5
  },
  {
    "seating_no": 1073861,
    "arabic_name": "جنى خالد عبدالله محمد",
    "total_degree": 257
  },
  {
    "seating_no": 1073862,
    "arabic_name": "جنى محمد محمود محمد حموده",
    "total_degree": 305
  },
  {
    "seating_no": 1073863,
    "arabic_name": "جهاد محمود محمد ابوسيف",
    "total_degree": 133
  },
  {
    "seating_no": 1073864,
    "arabic_name": "جودى رمضان رشوان صالح",
    "total_degree": 160.5
  },
  {
    "seating_no": 1073865,
    "arabic_name": "جودى محمد احمد عبدالوهاب محمود",
    "total_degree": 141.5
  },
  {
    "seating_no": 1073866,
    "arabic_name": "جيداء جابر محمد قاسم",
    "total_degree": 192
  },
  {
    "seating_no": 1073867,
    "arabic_name": "جيلان عبادى فتحى عبدالحميد",
    "total_degree": 302
  },
  {
    "seating_no": 1073868,
    "arabic_name": "جيهان محمد فرج معيزيق",
    "total_degree": 157
  },
  {
    "seating_no": 1073869,
    "arabic_name": "حبيبه احمد صبحى محمود",
    "total_degree": 195
  },
  {
    "seating_no": 1073870,
    "arabic_name": "حبيبه احمد محمد على",
    "total_degree": 272.5
  },
  {
    "seating_no": 1073871,
    "arabic_name": "حبيبه احمد نعيم عبدالحميد",
    "total_degree": 176.5
  },
  {
    "seating_no": 1073872,
    "arabic_name": "حبيبه السيد محمود محمود جمعه",
    "total_degree": 247.5
  },
  {
    "seating_no": 1073873,
    "arabic_name": "حبيبه جمال مصطفى حامد",
    "total_degree": 266
  },
  {
    "seating_no": 1073874,
    "arabic_name": "حبيبه حسن محمد محمود",
    "total_degree": 226
  },
  {
    "seating_no": 1073875,
    "arabic_name": "حبيبه حسين ربيع محمد",
    "total_degree": 214
  },
  {
    "seating_no": 1073876,
    "arabic_name": "حبيبه ربيع قطب على",
    "total_degree": 181.5
  },
  {
    "seating_no": 1073877,
    "arabic_name": "حبيبه رجب عيد على",
    "total_degree": 175.5
  },
  {
    "seating_no": 1073878,
    "arabic_name": "حبيبه رمضان عبدالرازق مراد",
    "total_degree": 168.5
  },
  {
    "seating_no": 1073879,
    "arabic_name": "حبيبه سيد محمد عفيفى محمد",
    "total_degree": 148
  },
  {
    "seating_no": 1073880,
    "arabic_name": "حبيبه شعبان فوزى شحاته",
    "total_degree": 186
  },
  {
    "seating_no": 1073881,
    "arabic_name": "حبيبه طلعت مسعود عبدالسلام",
    "total_degree": 147
  },
  {
    "seating_no": 1073882,
    "arabic_name": "حبيبه عادل على محمد حسان",
    "total_degree": 204
  },
  {
    "seating_no": 1073883,
    "arabic_name": "حبيبه عماد زيدان مناوي",
    "total_degree": 251
  },
  {
    "seating_no": 1073884,
    "arabic_name": "حبيبه عمرو شلبي عبدالتواب",
    "total_degree": 191
  },
  {
    "seating_no": 1073885,
    "arabic_name": "حبيبه محمد عيد رمضان",
    "total_degree": 187.5
  },
  {
    "seating_no": 1073886,
    "arabic_name": "حبيبه محمد ممدوح ابراهيم",
    "total_degree": 224.5
  },
  {
    "seating_no": 1073887,
    "arabic_name": "حبيبه محمود ابراهيم على",
    "total_degree": 240
  },
  {
    "seating_no": 1073888,
    "arabic_name": "حبيبه محمود عويس قرنى",
    "total_degree": 263.5
  },
  {
    "seating_no": 1073889,
    "arabic_name": "حبيبه محمود محمد سيد",
    "total_degree": 241.5
  },
  {
    "seating_no": 1073890,
    "arabic_name": "حبيبه ممدوح عبدالعظيم احمد",
    "total_degree": 172
  },
  {
    "seating_no": 1073891,
    "arabic_name": "حبيبه هانى انور سيد محمد",
    "total_degree": 235.5
  },
  {
    "seating_no": 1073892,
    "arabic_name": "حبيبه وليد حمدى سيد",
    "total_degree": 297.5
  },
  {
    "seating_no": 1073893,
    "arabic_name": "حبيبه ياسر اسماعيل سليمان سيد",
    "total_degree": 164.5
  },
  {
    "seating_no": 1073894,
    "arabic_name": "حسناء محروس ربيع عبدالحليم",
    "total_degree": 215
  },
  {
    "seating_no": 1073895,
    "arabic_name": "حسناء محمد عبدالرازق ميزار",
    "total_degree": 211
  },
  {
    "seating_no": 1073896,
    "arabic_name": "حسناء محمود محمد احمد",
    "total_degree": 226
  },
  {
    "seating_no": 1073897,
    "arabic_name": "حسناء وائل فتحى على محمد",
    "total_degree": 231.5
  },
  {
    "seating_no": 1073898,
    "arabic_name": "حلا طارق سيد على",
    "total_degree": 268.5
  },
  {
    "seating_no": 1073899,
    "arabic_name": "حنان رجب عبدالغني علي",
    "total_degree": 193
  },
  {
    "seating_no": 1073900,
    "arabic_name": "حنين اشرف احمد عبدالرحيم محمد",
    "total_degree": 293
  },
  {
    "seating_no": 1073901,
    "arabic_name": "حنين مهدى محمد رضوان",
    "total_degree": 210.5
  },
  {
    "seating_no": 1073902,
    "arabic_name": "خديجه ابراهيم عبدالعظيم ابراهيم",
    "total_degree": 192
  },
  {
    "seating_no": 1073903,
    "arabic_name": "خلود رجب جربوع عبدالعاطي",
    "total_degree": 161.5
  },
  {
    "seating_no": 1073904,
    "arabic_name": "خلود سعد احمد محمد",
    "total_degree": 253
  },
  {
    "seating_no": 1073905,
    "arabic_name": "داليا احمد عبدالظاهر عبدالحليم",
    "total_degree": 137.5
  },
  {
    "seating_no": 1073906,
    "arabic_name": "داليا عبدالجواد امين ابوزيد",
    "total_degree": 156.5
  },
  {
    "seating_no": 1073907,
    "arabic_name": "داليا محمد مصطفي على",
    "total_degree": 174
  },
  {
    "seating_no": 1073908,
    "arabic_name": "دعاء امام عبدالحميد محمد",
    "total_degree": 170.5
  },
  {
    "seating_no": 1073909,
    "arabic_name": "دعاء عبدالتواب شعبان احمد",
    "total_degree": 169.5
  },
  {
    "seating_no": 1073910,
    "arabic_name": "دعاء فضل الله محمود مسعود",
    "total_degree": 140
  },
  {
    "seating_no": 1073911,
    "arabic_name": "دعاء محمد قرنى السيد",
    "total_degree": 198
  },
  {
    "seating_no": 1073912,
    "arabic_name": "دعاء محمود احمد عطيه",
    "total_degree": 235.5
  },
  {
    "seating_no": 1073913,
    "arabic_name": "دنيا حماد فوزى عبدالكريم",
    "total_degree": 205.5
  },
  {
    "seating_no": 1073914,
    "arabic_name": "دنيا رجب عبدالعزيز على",
    "total_degree": 209.5
  },
  {
    "seating_no": 1073915,
    "arabic_name": "دنيا محمد محمود محمد",
    "total_degree": 130
  },
  {
    "seating_no": 1073916,
    "arabic_name": "دينا حسين رمضان عبدالرحيم",
    "total_degree": 206
  },
  {
    "seating_no": 1073917,
    "arabic_name": "دينا رجب عبدالعزيز على",
    "total_degree": 176
  },
  {
    "seating_no": 1073918,
    "arabic_name": "دينا محمد احمد عبدالموجود",
    "total_degree": 69.5
  },
  {
    "seating_no": 1073919,
    "arabic_name": "دينا محمود عبدالله طلب",
    "total_degree": 166.5
  },
  {
    "seating_no": 1073920,
    "arabic_name": "دينا مصطفى محمد هلال",
    "total_degree": 229.5
  },
  {
    "seating_no": 1073921,
    "arabic_name": "رؤى حسين صوفى زيدان",
    "total_degree": 182.5
  },
  {
    "seating_no": 1073922,
    "arabic_name": "رؤى محمود محمد عثمان",
    "total_degree": 291
  },
  {
    "seating_no": 1073923,
    "arabic_name": "رانيا محمود سيد عبدالغنى",
    "total_degree": 230
  },
  {
    "seating_no": 1073924,
    "arabic_name": "رانيا نصر محمد يوسف",
    "total_degree": 207
  },
  {
    "seating_no": 1073926,
    "arabic_name": "رباب ايمن عبدالرازق ابراهيم",
    "total_degree": 195
  },
  {
    "seating_no": 1073927,
    "arabic_name": "رحاب عيد عبدالهادى عبدالسلام",
    "total_degree": 191
  },
  {
    "seating_no": 1073928,
    "arabic_name": "رحمه احمد محمد رمضان",
    "total_degree": 232
  },
  {
    "seating_no": 1073929,
    "arabic_name": "رحمه ربيع جابر عبدالباسط",
    "total_degree": 160
  },
  {
    "seating_no": 1073930,
    "arabic_name": "رحمه عبدالحميد سليم بسيس",
    "total_degree": 158
  },
  {
    "seating_no": 1073931,
    "arabic_name": "رحمه محسن عواد عبدالله",
    "total_degree": 227.5
  },
  {
    "seating_no": 1073932,
    "arabic_name": "رحمه مصطفى انيس مصطفى",
    "total_degree": 139.5
  },
  {
    "seating_no": 1073933,
    "arabic_name": "رحمه ممدوح توفيق عبدالجواد",
    "total_degree": 213
  },
  {
    "seating_no": 1073934,
    "arabic_name": "رضوى خالد احمد محمد",
    "total_degree": 133
  },
  {
    "seating_no": 1073935,
    "arabic_name": "رضوى طارق محمد سليمان على",
    "total_degree": 197
  },
  {
    "seating_no": 1073936,
    "arabic_name": "رضوى عثمان عرفه قرنى",
    "total_degree": 222
  },
  {
    "seating_no": 1073937,
    "arabic_name": "رضوى محمد رمضان سيداحمد",
    "total_degree": 158
  },
  {
    "seating_no": 1073938,
    "arabic_name": "رغد محمد امين محمد",
    "total_degree": 253.5
  },
  {
    "seating_no": 1073939,
    "arabic_name": "رنا محمود محمود محمد",
    "total_degree": 234
  },
  {
    "seating_no": 1073940,
    "arabic_name": "رناد توبه السيد عبدالتواب",
    "total_degree": 175.5
  },
  {
    "seating_no": 1073941,
    "arabic_name": "رناد عماد كمال احمد",
    "total_degree": 204
  },
  {
    "seating_no": 1073942,
    "arabic_name": "روان محمود طه محمود",
    "total_degree": 250.5
  },
  {
    "seating_no": 1073943,
    "arabic_name": "روان مصطفى كامل محمد",
    "total_degree": 235.5
  },
  {
    "seating_no": 1073944,
    "arabic_name": "روجينا عادل حسنى عمار",
    "total_degree": 173.5
  },
  {
    "seating_no": 1073945,
    "arabic_name": "روفيدا محمد محمد شاكر",
    "total_degree": 196.5
  },
  {
    "seating_no": 1073946,
    "arabic_name": "روفيدا مصطفى امين محمد",
    "total_degree": 228.5
  },
  {
    "seating_no": 1073947,
    "arabic_name": "رويدا احمد محمد شعبان",
    "total_degree": 207.5
  },
  {
    "seating_no": 1073948,
    "arabic_name": "رويدا سعد محمد عبدالهادى",
    "total_degree": 145.5
  },
  {
    "seating_no": 1073949,
    "arabic_name": "ريتاج ممدوح عبدالعليم عبدالرازق",
    "total_degree": 162.5
  },
  {
    "seating_no": 1073950,
    "arabic_name": "ريم السيد حسنى عبدالتواب",
    "total_degree": 206
  },
  {
    "seating_no": 1073951,
    "arabic_name": "ريم جمال محمود عبدالله",
    "total_degree": 159
  },
  {
    "seating_no": 1073952,
    "arabic_name": "ريم حماده كامل محمد",
    "total_degree": 196
  },
  {
    "seating_no": 1073953,
    "arabic_name": "ريم رمضان جمعه عبدالصادق",
    "total_degree": 179.5
  },
  {
    "seating_no": 1073954,
    "arabic_name": "ريم عماد مشرف عبدالعليم",
    "total_degree": 197
  },
  {
    "seating_no": 1073955,
    "arabic_name": "ريم محمد فتحى على",
    "total_degree": 91.5
  },
  {
    "seating_no": 1073956,
    "arabic_name": "ريم محمد محمود على عبدالمقصود",
    "total_degree": 290.5
  },
  {
    "seating_no": 1073957,
    "arabic_name": "ريهام اسماعيل عثمان اسماعيل",
    "total_degree": 210.5
  },
  {
    "seating_no": 1073958,
    "arabic_name": "ريهام اشرف سعداوى عبدالسلام",
    "total_degree": 219.5
  },
  {
    "seating_no": 1073959,
    "arabic_name": "ريهام عادل محمود محمد",
    "total_degree": 263.5
  },
  {
    "seating_no": 1073960,
    "arabic_name": "ريهام عفت مصطفي جبريل",
    "total_degree": 146
  },
  {
    "seating_no": 1073961,
    "arabic_name": "ريهام عيد محمد الصاوى",
    "total_degree": 164.5
  },
  {
    "seating_no": 1073962,
    "arabic_name": "زينب هانى اسماعيل قرشى",
    "total_degree": 237.5
  },
  {
    "seating_no": 1073963,
    "arabic_name": "ساره احمد محمد محمود",
    "total_degree": 218
  },
  {
    "seating_no": 1073964,
    "arabic_name": "ساره جمال احمد محمود محمد",
    "total_degree": 219
  },
  {
    "seating_no": 1073965,
    "arabic_name": "ساره ربيع محمد احمد",
    "total_degree": 256
  },
  {
    "seating_no": 1073966,
    "arabic_name": "ساره سالم محمد عبدالسلام",
    "total_degree": 148
  },
  {
    "seating_no": 1073967,
    "arabic_name": "ساره عاشور قنديل محمد",
    "total_degree": 232
  },
  {
    "seating_no": 1073968,
    "arabic_name": "ساره عبدالتواب احمد عبدالله",
    "total_degree": 167.5
  },
  {
    "seating_no": 1073969,
    "arabic_name": "ساره عبدالمحسن احمد عبدالمحسن",
    "total_degree": 167.5
  },
  {
    "seating_no": 1073970,
    "arabic_name": "ساره عبدالناصر محمد السيد",
    "total_degree": 190
  },
  {
    "seating_no": 1073971,
    "arabic_name": "ساره عزت صالح رزق",
    "total_degree": 218.5
  },
  {
    "seating_no": 1073972,
    "arabic_name": "ساره عزت محمد احمد",
    "total_degree": 134.5
  },
  {
    "seating_no": 1073973,
    "arabic_name": "ساره فارس محمد محمد",
    "total_degree": 173.5
  },
  {
    "seating_no": 1073974,
    "arabic_name": "ساره محسن عويس عبدالقادر",
    "total_degree": 111.5
  },
  {
    "seating_no": 1073975,
    "arabic_name": "ساره محمد رمضان على",
    "total_degree": 183
  },
  {
    "seating_no": 1073976,
    "arabic_name": "ساره محمد عبدالتواب ميلاد",
    "total_degree": 189
  },
  {
    "seating_no": 1073977,
    "arabic_name": "ساره محمد مصطفى حسن",
    "total_degree": 166
  },
  {
    "seating_no": 1073978,
    "arabic_name": "سحر خميس عبدالهادى جوده",
    "total_degree": 262
  },
  {
    "seating_no": 1073979,
    "arabic_name": "سلسبيل خالد سعد محمود",
    "total_degree": 210.5
  },
  {
    "seating_no": 1073980,
    "arabic_name": "سلسبيلا سيد عبدالله سعد",
    "total_degree": 217
  },
  {
    "seating_no": 1073981,
    "arabic_name": "سلمى ابراهيم محمد احمد",
    "total_degree": 282.5
  },
  {
    "seating_no": 1073982,
    "arabic_name": "سلمى احمد قاسم احمد",
    "total_degree": 188.5
  },
  {
    "seating_no": 1073983,
    "arabic_name": "سلمى احمد محمد محمد",
    "total_degree": 282.5
  },
  {
    "seating_no": 1073984,
    "arabic_name": "سلمى حسام الدين مصطفى محمود",
    "total_degree": 254
  },
  {
    "seating_no": 1073985,
    "arabic_name": "سلمى طارق محمد ابراهيم",
    "total_degree": 138.5
  },
  {
    "seating_no": 1073986,
    "arabic_name": "سلمى طه محمد يونس",
    "total_degree": 163
  },
  {
    "seating_no": 1073987,
    "arabic_name": "سلمى عصام الدين مصطفي سيد",
    "total_degree": 284
  },
  {
    "seating_no": 1073988,
    "arabic_name": "سلمى محمد ميهوب محمد",
    "total_degree": 158
  },
  {
    "seating_no": 1073989,
    "arabic_name": "سلمى ياسر محمد احمد مرسى",
    "total_degree": 238
  },
  {
    "seating_no": 1073990,
    "arabic_name": "سما اشرف محمد السيد",
    "total_degree": 208.5
  },
  {
    "seating_no": 1073991,
    "arabic_name": "سما شوقى السيد فرج",
    "total_degree": 216
  },
  {
    "seating_no": 1073992,
    "arabic_name": "سما عاطف احمد مصطفى",
    "total_degree": 0
  },
  {
    "seating_no": 1073993,
    "arabic_name": "سما على قرنى خميس",
    "total_degree": 190.5
  },
  {
    "seating_no": 1073994,
    "arabic_name": "سما نجم عبداللطيف معروف",
    "total_degree": 196
  },
  {
    "seating_no": 1073995,
    "arabic_name": "سماح عصام حسان سعد حسان",
    "total_degree": 195.5
  },
  {
    "seating_no": 1073996,
    "arabic_name": "سميه احمد احمد جمعه",
    "total_degree": 286
  },
  {
    "seating_no": 1073997,
    "arabic_name": "سميه محمد كمال على",
    "total_degree": 164
  },
  {
    "seating_no": 1073998,
    "arabic_name": "سميه مصطفى شحاته عبدالمحسن",
    "total_degree": 176
  },
  {
    "seating_no": 1073999,
    "arabic_name": "سميه ياسر محمد بركات",
    "total_degree": 154
  }
]